Workbook

Sheet Main
A1: RestaurantID | B1: RestaurantName | C1: CountryCode | D1: City | E1: Locality | F1: Longitude | G1: Latitude | H1: Cuisines | I1: Currency | J1: Has_Table_booking | K1: Has_Online_delivery | L1: Is_delivering_now | M1: Switch_to_order_menu | N1: Price_range | O1: Votes | P1: Average_Cost_for_two | Q1: Rating | R1: Year Opening | S1: Month Opening | T1: Day Opening | U1: Date | V1: Avg_Cost_USD | W1: Price_Bucket
A2: 18435314 | B2: Punjabi's Veg Grill | C2: 1 | D2: New Delhi | E2: Geeta Colony | F2: 77.276769 | G2: 28.650775 | H2: North Indian | I2: Indian Rupees(Rs.) | J2: No | K2: No | L2: No | M2: No | N2: 1 | O2: 0 | P2: 300 | Q2: 1 | R2: 2013 | S2: 9 | T2: 21 | U2: 41538 | V2: =Main[[#This Row],[Average_Cost_for_two]] * VLOOKUP(Main[[#This Row],[Currency]],'Currency'!A:B,2,FALSE) -> 3.6 | W2: =IF(Main[[#This Row],[Avg_Cost_USD]]<10,"Low", IF(Main[[#This Row],[Avg_Cost_USD]]<=30,"Medium","High")) -> Low
A3: 18378015 | B3: Tasty Tandoor | C3: 1 | D3: New Delhi | E3: Geeta Colony | F3: 77.275052 | G3: 28.658216 | H3: North Indian | I3: Indian Rupees(Rs.) | J3: No | K3: No | L3: No | M3: No | N3: 1 | O3: 0 | P3: 200 | Q3: 1 | R3: 2016 | S3: 9 | T3: 10 | U3: 42623 | V3: =Main[[#This Row],[Average_Cost_for_two]] * VLOOKUP(Main[[#This Row],[Currency]],'Currency'!A:B,2,FALSE) -> 2.4 | W3: =IF(Main[[#This Row],[Avg_Cost_USD]]<10,"Low", IF(Main[[#This Row],[Avg_Cost_USD]]<=30,"Medium","High")) -> Low
A4: 18424905 | B4: Taste of Spice | C4: 1 | D4: New Delhi | E4: Lajpat Nagar 1 | F4: 77.241312 | G4: 28.578311 | H4: North Indian | I4: Indian Rupees(Rs.) | J4: No | K4: Yes | L4: No | M4: No | N4: 1 | O4: 0 | P4: 400 | Q4: 1 | R4: 2018 | S4: 9 | T4: 25 | U4: 43368 | V4: =Main[[#This Row],[Average_Cost_for_two]] * VLOOKUP(Main[[#This Row],[Currency]],'Currency'!A:B,2,FALSE) -> 4.8 | W4: =IF(Main[[#This Row],[Avg_Cost_USD]]<10,"Low", IF(Main[[#This Row],[Avg_Cost_USD]]<=30,"Medium","High")) -> Low
A5: 18180072 | B5: Kolcata Bengali Dhaba | C5: 1 | D5: New Delhi | E5: Mahipalpur | F5: 77.123932 | G5: 28.543587 | H5: North Indian | I5: Indian Rupees(Rs.) | J5: No | K5: No | L5: No | M5: No | N5: 1 | O5: 0 | P5: 100 | Q5: 1 | R5: 2018 | S5: 9 | T5: 6 | U5: 43349 | V5: =Main[[#This Row],[Average_Cost_for_two]] * VLOOKUP(Main[[#This Row],[Currency]],'Currency'!A:B,2,FALSE) -> 1.2 | W5: =IF(Main[[#This Row],[Avg_Cost_USD]]<10,"Low", IF(Main[[#This Row],[Avg_Cost_USD]]<=30,"Medium","High")) -> Low
A6: 18415377 | B6: Sunil Punjabi Dhaba | C6: 1 | D6: New Delhi | E6: Mahipalpur | F6: 77.129706 | G6: 28.541369 | H6: North Indian | I6: Indian Rupees(Rs.) | J6: No | K6: No | L6: No | M6: No | N6: 1 | O6: 0 | P6: 150 | Q6: 1 | R6: 2013 | S6: 9 | T6: 17 | U6: 41534 | V6: =Main[[#This Row],[Average_Cost_for_two]] * VLOOKUP(Main[[#This Row],[Currency]],'Currency'!A:B,2,FALSE) -> 1.8 | W6: =IF(Main[[#This Row],[Avg_Cost_USD]]<10,"Low", IF(Main[[#This Row],[Avg_Cost_USD]]<=30,"Medium","High")) -> Low
A7: 18421485 | B7: Bikaner Restaurant | C7: 1 | D7: New Delhi | E7: Mukherjee Nagar | F7: 77.208135 | G7: 28.699566 | H7: North Indian | I7: Indian Rupees(Rs.) | J7: No | K7: No | L7: No | M7: No | N7: 1 | O7: 0 | P7: 100 | Q7: 1 | R7: 2018 | S7: 9 | T7: 3 | U7: 43346 | V7: =Main[[#This Row],[Average_Cost_for_two]] * VLOOKUP(Main[[#This Row],[Currency]],'Currency'!A:B,2,FALSE) -> 1.2 | W7: =IF(Main[[#This Row],[Avg_Cost_USD]]<10,"Low", IF(Main[[#This Row],[Avg_Cost_USD]]<=30,"Medium","High")) -> Low
A8: 312413 | B8: Just In | C8: 1 | D8: New Delhi | E8: Mukherjee Nagar | F8: 77.219094 | G8: 28.70948 | H8: North Indian | I8: Indian Rupees(Rs.) | J8: No | K8: No | L8: No | M8: No | N8: 1 | O8: 0 | P8: 200 | Q8: 1 | R8: 2011 | S8: 9 | T8: 16 | U8: 40802 | V8: =Main[[#This Row],[Average_Cost_for_two]] * VLOOKUP(Main[[#This Row],[Currency]],'Currency'!A:B,2,FALSE) -> 2.4 | W8: =IF(Main[[#This Row],[Avg_Cost_USD]]<10,"Low", IF(Main[[#This Row],[Avg_Cost_USD]]<=30,"Medium","High")) -> Low
A9: 303497 | B9: Shri Shyam Ji Shudh Shakahari Bhojnalaya | C9: 1 | D9: New Delhi | E9: Najafgarh | F9: 76.974892 | G9: 28.611254 | H9: North Indian | I9: Indian Rupees(Rs.) | J9: No | K9: No | L9: No | M9: No | N9: 1 | O9: 0 | P9: 150 | Q9: 1 | R9: 2014 | S9: 9 | T9: 21 | U9: 41903 | V9: =Main[[#This Row],[Average_Cost_for_two]] * VLOOKUP(Main[[#This Row],[Currency]],'Currency'!A:B,2,FALSE) -> 1.8 | W9: =IF(Main[[#This Row],[Avg_Cost_USD]]<10,"Low", IF(Main[[#This Row],[Avg_Cost_USD]]<=30,"Medium","High")) -> Low
A10: 18354644 | B10: Shree Bhojnalaya | C10: 1 | D10: New Delhi | E10: New Friends Colony | F10: 77.272762 | G10: 28.560771 | H10: North Indian | I10: Indian Rupees(Rs.) | J10: No | K10: No | L10: No | M10: No | N10: 1 | O10: 0 | P10: 100 | Q10: 1 | R10: 2012 | S10: 9 | T10: 9 | U10: 41161 | V10: =Main[[#This Row],[Average_Cost_for_two]] * VLOOKUP(Main[[#This Row],[Currency]],'Currency'!A:B,2,FALSE) -> 1.2 | W10: =IF(Main[[#This Row],[Avg_Cost_USD]]<10,"Low", IF(Main[[#This Row],[Avg_Cost_USD]]<=30,"Medium","High")) -> Low
A11: 18366001 | B11: Baba Ka Dhaba | C11: 1 | D11: New Delhi | E11: Palam | F11: 77.09028 | G11: 28.582898 | H11: North Indian | I11: Indian Rupees(Rs.) | J11: No | K11: No | L11: No | M11: No | N11: 1 | O11: 0 | P11: 200 | Q11: 1 | R11: 2014 | S11: 9 | T11: 21 | U11: 41903 | V11: =Main[[#This Row],[Average_Cost_for_two]] * VLOOKUP(Main[[#This Row],[Currency]],'Currency'!A:B,2,FALSE) -> 2.4 | W11: =IF(Main[[#This Row],[Avg_Cost_USD]]<10,"Low", IF(Main[[#This Row],[Avg_Cost_USD]]<=30,"Medium","High")) -> Low
A12: 18486845 | B12: Kaka Da Dhaba | C12: 1 | D12: New Delhi | E12: R K Puram | F12: 77.174118 | G12: 28.577193 | H12: North Indian | I12: Indian Rupees(Rs.) | J12: No | K12: No | L12: No | M12: No | N12: 1 | O12: 0 | P12: 100 | Q12: 1 | R12: 2012 | S12: 9 | T12: 24 | U12: 41176 | V12: =Main[[#This Row],[Average_Cost_for_two]] * VLOOKUP(Main[[#This Row],[Currency]],'Currency'!A:B,2,FALSE) -> 1.2 | W12: =IF(Main[[#This Row],[Avg_Cost_USD]]<10,"Low", IF(Main[[#This Row],[Avg_Cost_USD]]<=30,"Medium","High")) -> Low
A13: 18424202 | B13: Famous Parantha and Poori Sabzi | C13: 1 | D13: New Delhi | E13: Vasundhara Enclave | F13: 77.308509 | G13: 28.589376 | H13: North Indian | I13: Indian Rupees(Rs.) | J13: No | K13: No | L13: No | M13: No | N13: 1 | O13: 0 | P13: 50 | Q13: 1 | R13: 2014 | S13: 9 | T13: 20 | U13: 41902 | V13: =Main[[#This Row],[Average_Cost_for_two]] * VLOOKUP(Main[[#This Row],[Currency]],'Currency'!A:B,2,FALSE) -> 0.6 | W13: =IF(Main[[#This Row],[Avg_Cost_USD]]<10,"Low", IF(Main[[#This Row],[Avg_Cost_USD]]<=30,"Medium","High")) -> Low
... A8655: 17334679 | B8655: Azteca | C8655: 216 | D8655: Davenport | E8655: Davenport | F8655: -90.5683 | G8655: 41.5699 | H8655: Mexican | I8655: Dollar($) | J8655: No | K8655: No | L8655: No | M8655: No | N8655: 1 | O8655: 167 | P8655: 0 | Q8655: 4.3 | R8655: 2015 | S8655: 9 | T8655: 28 | U8655: 42275 | V8655: =Main[[#This Row],[Average_Cost_for_two]] * VLOOKUP(Main[[#This Row],[Currency]],'Currency'!A:B,2,FALSE) -> 0 | W8655: =IF(Main[[#This Row],[Avg_Cost_USD]]<10,"Low", IF(Main[[#This Row],[Avg_Cost_USD]]<=30,"Medium","High")) -> Low
A8656: 17606621 | B8656: HI Lite Bar & Lounge | C8656: 216 | D8656: Miller | E8656: Miller | F8656: -98.9891 | G8656: 44.5158 | I8656: Dollar($) | J8656: No | K8656: No | L8656: No | M8656: No | N8656: 1 | O8656: 11 | P8656: 0 | Q8656: 3.4 | R8656: 2013 | S8656: 9 | T8656: 9 | U8656: 41526 | V8656: =Main[[#This Row],[Average_Cost_for_two]] * VLOOKUP(Main[[#This Row],[Currency]],'Currency'!A:B,2,FALSE) -> 0 | W8656: =IF(Main[[#This Row],[Avg_Cost_USD]]<10,"Low", IF(Main[[#This Row],[Avg_Cost_USD]]<=30,"Medium","High")) -> Low
A8657: 17582627 | B8657: Senor Iguanas | C8657: 216 | D8657: Pocatello | E8657: Pocatello | F8657: -112.4433 | G8657: 42.8942 | H8657: Mexican | I8657: Dollar($) | J8657: No | K8657: No | L8657: No | M8657: No | N8657: 1 | O8657: 108 | P8657: 0 | Q8657: 3.6 | R8657: 2017 | S8657: 9 | T8657: 1 | U8657: 42979 | V8657: =Main[[#This Row],[Average_Cost_for_two]] * VLOOKUP(Main[[#This Row],[Currency]],'Currency'!A:B,2,FALSE) -> 0 | W8657: =IF(Main[[#This Row],[Avg_Cost_USD]]<10,"Low", IF(Main[[#This Row],[Avg_Cost_USD]]<=30,"Medium","High")) -> Low
A8658: 2148 | B8658: 56 Ristorante Italiano | C8658: 1 | D8658: Gurgaon | E8658: Golf Course Road | F8658: 77.101996 | G8658: 28.440092 | H8658: Italian | I8658: Indian Rupees(Rs.) | J8658: Yes | K8658: Yes | L8658: No | M8658: No | N8658: 4 | O8658: 416 | P8658: 2200 | Q8658: 3.7 | R8658: 2010 | S8658: 1 | T8658: 9 | U8658: 40187 | V8658: =Main[[#This Row],[Average_Cost_for_two]] * VLOOKUP(Main[[#This Row],[Currency]],'Currency'!A:B,2,FALSE) -> 26.4 | W8658: =IF(Main[[#This Row],[Avg_Cost_USD]]<10,"Low", IF(Main[[#This Row],[Avg_Cost_USD]]<=30,"Medium","High")) -> Medium
A8659: 18317498 | B8659: The Butler & The Chef - Jaypee Greens | C8659: 1 | D8659: Noida | E8659: Jaypee Greens, Greater Noida, Noida | F8659: 77.521526 | G8659: 28.464167 | H8659: Finger Food | I8659: Indian Rupees(Rs.) | J8659: Yes | K8659: No | L8659: No | M8659: No | N8659: 4 | O8659: 1 | P8659: 2200 | Q8659: 1 | R8659: 2016 | S8659: 4 | T8659: 6 | U8659: 42466 | V8659: =Main[[#This Row],[Average_Cost_for_two]] * VLOOKUP(Main[[#This Row],[Currency]],'Currency'!A:B,2,FALSE) -> 26.4 | W8659: =IF(Main[[#This Row],[Avg_Cost_USD]]<10,"Low", IF(Main[[#This Row],[Avg_Cost_USD]]<=30,"Medium","High")) -> Medium
A8660: 3226 | B8660: Flluid - Mosaic Hotels | C8660: 1 | D8660: Noida | E8660: Mosaic Hotels, Sector 18, Noida | F8660: 77.325545 | G8660: 28.57102 | H8660: Continental, North Indian, Mexican | I8660: Indian Rupees(Rs.) | J8660: Yes | K8660: No | L8660: No | M8660: No | N8660: 4 | O8660: 135 | P8660: 2200 | Q8660: 3.2 | R8660: 2015 | S8660: 9 | T8660: 10 | U8660: 42257 | V8660: =Main[[#This Row],[Average_Cost_for_two]] * VLOOKUP(Main[[#This Row],[Currency]],'Currency'!A:B,2,FALSE) -> 26.4 | W8660: =IF(Main[[#This Row],[Avg_Cost_USD]]<10,"Low", IF(Main[[#This Row],[Avg_Cost_USD]]<=30,"Medium","High")) -> Medium
A8661: 4248 | B8661: The Great Kabab Factory | C8661: 1 | D8661: Noida | E8661: Sector 18 | F8661: 77.32181 | G8661: 28.572104 | H8661: North Indian, Mughlai | I8661: Indian Rupees(Rs.) | J8661: Yes | K8661: No | L8661: No | M8661: No | N8661: 4 | O8661: 540 | P8661: 2200 | Q8661: 3.5 | R8661: 2018 | S8661: 1 | T8661: 26 | U8661: 43126 | V8661: =Main[[#This Row],[Average_Cost_for_two]] * VLOOKUP(Main[[#This Row],[Currency]],'Currency'!A:B,2,FALSE) -> 26.4 | W8661: =IF(Main[[#This Row],[Avg_Cost_USD]]<10,"Low", IF(Main[[#This Row],[Avg_Cost_USD]]<=30,"Medium","High")) -> Medium
A8662: 17582524 | B8662: Butterburrs | C8662: 216 | D8662: Pocatello | E8662: Pocatello | F8662: -112.4516 | G8662: 42.8919 | H8662: American, Breakfast | I8662: Dollar($) | J8662: No | K8662: No | L8662: No | M8662: No | N8662: 3 | O8662: 121 | P8662: 30 | Q8662: 3.6 | R8662: 2016 | S8662: 7 | T8662: 25 | U8662: 42576 | V8662: =Main[[#This Row],[Average_Cost_for_two]] * VLOOKUP(Main[[#This Row],[Currency]],'Currency'!A:B,2,FALSE) -> 30 | W8662: =IF(Main[[#This Row],[Avg_Cost_USD]]<10,"Low", IF(Main[[#This Row],[Avg_Cost_USD]]<=30,"Medium","High")) -> Medium
A8663: 17144991 | B8663: Coconuts Fish Cafe | C8663: 216 | D8663: Rest of Hawaii | E8663: Kihei | F8663: -156.45528 | G8663: 20.748838 | H8663: Seafood | I8663: Dollar($) | J8663: No | K8663: No | L8663: No | M8663: No | N8663: 3 | O8663: 487 | P8663: 30 | Q8663: 4.5 | R8663: 2010 | S8663: 7 | T8663: 24 | U8663: 40383 | V8663: =Main[[#This Row],[Average_Cost_for_two]] * VLOOKUP(Main[[#This Row],[Currency]],'Currency'!A:B,2,FALSE) -> 30 | W8663: =IF(Main[[#This Row],[Avg_Cost_USD]]<10,"Low", IF(Main[[#This Row],[Avg_Cost_USD]]<=30,"Medium","High")) -> Medium
A8664: 121120 | B8664: Virgin Courtyard | C8664: 1 | D8664: Chandigarh | E8664: Sector 7 | F8664: 76.79762 | G8664: 30.73348 | H8664: Italian | I8664: Indian Rupees(Rs.) | J8664: No | K8664: No | L8664: No | M8664: No | N8664: 4 | O8664: 817 | P8664: 2200 | Q8664: 4.4 | R8664: 2010 | S8664: 6 | T8664: 11 | U8664: 40340 | V8664: =Main[[#This Row],[Average_Cost_for_two]] * VLOOKUP(Main[[#This Row],[Currency]],'Currency'!A:B,2,FALSE) -> 26.4 | W8664: =IF(Main[[#This Row],[Avg_Cost_USD]]<10,"Low", IF(Main[[#This Row],[Avg_Cost_USD]]<=30,"Medium","High")) -> Medium
A8665: 306581 | B8665: The Hungry Monkey | C8665: 1 | D8665: New Delhi | E8665: Safdarjung | F8665: 77.196097 | G8665: 28.559007 | H8665: European, Italian | I8665: Indian Rupees(Rs.) | J8665: Yes | K8665: No | L8665: No | M8665: No | N8665: 4 | O8665: 622 | P8665: 2300 | Q8665: 3.7 | R8665: 2010 | S8665: 11 | T8665: 8 | U8665: 40490 | V8665: =Main[[#This Row],[Average_Cost_for_two]] * VLOOKUP(Main[[#This Row],[Currency]],'Currency'!A:B,2,FALSE) -> 27.6 | W8665: =IF(Main[[#This Row],[Avg_Cost_USD]]<10,"Low", IF(Main[[#This Row],[Avg_Cost_USD]]<=30,"Medium","High")) -> Medium
A8666: 308016 | B8666: Sutra Gastropub | C8666: 1 | D8666: Gurgaon | E8666: Cyber Hub, DLF Cyber City | F8666: 77.088328 | G8666: 28.494815 | H8666: Mediterranean, European, American, North Indian | I8666: Indian Rupees(Rs.) | J8666: No | K8666: No | L8666: No | M8666: No | N8666: 4 | O8666: 1046 | P8666: 2300 | Q8666: 3.8 | R8666: 2011 | S8666: 10 | T8666: 17 | U8666: 40833 | V8666: =Main[[#This Row],[Average_Cost_for_two]] * VLOOKUP(Main[[#This Row],[Currency]],'Currency'!A:B,2,FALSE) -> 27.6 | W8666: =IF(Main[[#This Row],[Avg_Cost_USD]]<10,"Low", IF(Main[[#This Row],[Avg_Cost_USD]]<=30,"Medium","High")) -> Medium
A8667: 102215 | B8667: Monarch Restaurant - Holiday Inn Jaipur City Centre | C8667: 1 | D8667: Jaipur | E8667: Holiday Inn Jaipur City Centre, Bais Godam | F8667: 75.793007 | G8667: 26.90294 | H8667: North Indian, Chinese, Continental, Rajasthani | I8667: Indian Rupees(Rs.) | J8667: No | K8667: No | L8667: No | M8667: No | N8667: 4 | O8667: 420 | P8667: 2300 | Q8667: 4.5 | R8667: 2013 | S8667: 5 | T8667: 6 | U8667: 41400 | V8667: =Main[[#This Row],[Average_Cost_for_two]] * VLOOKUP(Main[[#This Row],[Currency]],'Currency'!A:B,2,FALSE) -> 27.6 | W8667: =IF(Main[[#This Row],[Avg_Cost_USD]]<10,"Low", IF(Main[[#This Row],[Avg_Cost_USD]]<=30,"Medium","High")) -> Medium
A8668: 18175334 | B8668: TFK - The Flaming Kick | C8668: 1 | D8668: Noida | E8668: Sector 18 | F8668: 77.322369 | G8668: 28.56955 | H8668: North Indian, Asian, Continental | I8668: Indian Rupees(Rs.) | J8668: Yes | K8668: Yes | L8668: No | M8668: No | N8668: 4 | O8668: 214 | P8668: 2350 | Q8668: 3.5 | R8668: 2015 | S8668: 5 | T8668: 9 | U8668: 42133 | V8668: =Main[[#This Row],[Average_Cost_for_two]] * VLOOKUP(Main[[#This Row],[Currency]],'Currency'!A:B,2,FALSE) -> 28.2 | W8668: =IF(Main[[#This Row],[Avg_Cost_USD]]<10,"Low", IF(Main[[#This Row],[Avg_Cost_USD]]<=30,"Medium","High")) -> Medium
A8669: 17284211 | B8669: Pearly's Famous Country Cookng | C8669: 216 | D8669: Albany | E8669: Albany | F8669: -84.1759 | G8669: 31.5882 | I8669: Dollar($) | J8669: No | K8669: No | L8669: No | M8669: No | N8669: 1 | O8669: 36 | P8669: 0 | Q8669: 3.4 | R8669: 2011 | S8669: 4 | T8669: 25 | U8669: 40658 | V8669: =Main[[#This Row],[Average_Cost_for_two]] * VLOOKUP(Main[[#This Row],[Currency]],'Currency'!A:B,2,FALSE) -> 0 | W8669: =IF(Main[[#This Row],[Avg_Cost_USD]]<10,"Low", IF(Main[[#This Row],[Avg_Cost_USD]]<=30,"Medium","High")) -> Low
A8670: 17064266 | B8670: Hawkers Asian Street Fare | C8670: 216 | D8670: Orlando | E8670: Mills 50 | F8670: -81.364347 | G8670: 28.560505 | H8670: Asian, Thai | I8670: Dollar($) | J8670: No | K8670: No | L8670: No | M8670: No | N8670: 3 | O8670: 1293 | P8670: 35 | Q8670: 4.6 | R8670: 2017 | S8670: 4 | T8670: 14 | U8670: 42839 | V8670: =Main[[#This Row],[Average_Cost_for_two]] * VLOOKUP(Main[[#This Row],[Currency]],'Currency'!A:B,2,FALSE) -> 35 | W8670: =IF(Main[[#This Row],[Avg_Cost_USD]]<10,"Low", IF(Main[[#This Row],[Avg_Cost_USD]]<=30,"Medium","High")) -> High
A8671: 307330 | B8671: Moonshine Cafe & Bar | C8671: 1 | D8671: New Delhi | E8671: Hauz Khas Village | F8671: 77.194159 | G8671: 28.554131 | H8671: Continental, Italian | I8671: Indian Rupees(Rs.) | J8671: No | K8671: No | L8671: No | M8671: No | N8671: 4 | O8671: 884 | P8671: 2400 | Q8671: 3.5 | R8671: 2014 | S8671: 3 | T8671: 5 | U8671: 41703 | V8671: =Main[[#This Row],[Average_Cost_for_two]] * VLOOKUP(Main[[#This Row],[Currency]],'Currency'!A:B,2,FALSE) -> 28.8 | W8671: =IF(Main[[#This Row],[Avg_Cost_USD]]<10,"Low", IF(Main[[#This Row],[Avg_Cost_USD]]<=30,"Medium","High")) -> Medium
A8672: 17061205 | B8672: Yellow Dog Eats | C8672: 216 | D8672: Orlando | E8672: Windermere | F8672: -81.522987 | G8672: 28.527592 | H8672: American, BBQ, Sandwich | I8672: Dollar($) | J8672: No | K8672: No | L8672: No | M8672: No | N8672: 3 | O8672: 1252 | P8672: 35 | Q8672: 4.9 | R8672: 2012 | S8672: 4 | T8672: 5 | U8672: 41004 | V8672: =Main[[#This Row],[Average_Cost_for_two]] * VLOOKUP(Main[[#This Row],[Currency]],'Currency'!A:B,2,FALSE) -> 35 | W8672: =IF(Main[[#This Row],[Avg_Cost_USD]]<10,"Low", IF(Main[[#This Row],[Avg_Cost_USD]]<=30,"Medium","High")) -> High
A8673: 17330155 | B8673: Deorio's | C8673: 216 | D8673: Columbus | E8673: Columbus | F8673: -84.9427 | G8673: 32.481 | H8673: Italian, Pizza | I8673: Dollar($) | J8673: No | K8673: No | L8673: No | M8673: No | N8673: 1 | O8673: 170 | P8673: 0 | Q8673: 4 | R8673: 2012 | S8673: 3 | T8673: 26 | U8673: 40994 | V8673: =Main[[#This Row],[Average_Cost_for_two]] * VLOOKUP(Main[[#This Row],[Currency]],'Currency'!A:B,2,FALSE) -> 0 | W8673: =IF(Main[[#This Row],[Avg_Cost_USD]]<10,"Low", IF(Main[[#This Row],[Avg_Cost_USD]]<=30,"Medium","High")) -> Low
A8674: 17582499 | B8674: Royal Hotel | C8674: 216 | D8674: Pocatello | E8674: Lava Hot Springs | F8674: -112.0127 | G8674: 42.6192 | H8674: Pizza, Bar Food | I8674: Dollar($) | J8674: No | K8674: No | L8674: No | M8674: No | N8674: 1 | O8674: 59 | P8674: 0 | Q8674: 3.6 | R8674: 2017 | S8674: 3 | T8674: 15 | U8674: 42809 | V8674: =Main[[#This Row],[Average_Cost_for_two]] * VLOOKUP(Main[[#This Row],[Currency]],'Currency'!A:B,2,FALSE) -> 0 | W8674: =IF(Main[[#This Row],[Avg_Cost_USD]]<10,"Low", IF(Main[[#This Row],[Avg_Cost_USD]]<=30,"Medium","High")) -> Low
A8675: 18359296 | B8675: Liquid | C8675: 1 | D8675: New Delhi | E8675: Prashant Vihar | F8675: 77.137506 | G8675: 28.71276 | H8675: North Indian, Mughlai, Chinese | I8675: Indian Rupees(Rs.) | J8675: Yes | K8675: No | L8675: No | M8675: No | N8675: 4 | O8675: 11 | P8675: 2400 | Q8675: 3.2 | R8675: 2011 | S8675: 12 | T8675: 2 | U8675: 40879 | V8675: =Main[[#This Row],[Average_Cost_for_two]] * VLOOKUP(Main[[#This Row],[Currency]],'Currency'!A:B,2,FALSE) -> 28.8 | W8675: =IF(Main[[#This Row],[Avg_Cost_USD]]<10,"Low", IF(Main[[#This Row],[Avg_Cost_USD]]<=30,"Medium","High")) -> Medium
A8676: 929 | B8676: Pebble Street | C8676: 1 | D8676: New Delhi | E8676: Community Centre, New Friends Colony | F8676: 77.268938 | G8676: 28.562538 | H8676: Italian, Tex-Mex, Continental, North Indian | I8676: Indian Rupees(Rs.) | J8676: Yes | K8676: Yes | L8676: No | M8676: No | N8676: 4 | O8676: 886 | P8676: 2400 | Q8676: 3.9 | R8676: 2018 | S8676: 10 | T8676: 8 | U8676: 43381 | V8676: =Main[[#This Row],[Average_Cost_for_two]] * VLOOKUP(Main[[#This Row],[Currency]],'Currency'!A:B,2,FALSE) -> 28.8 | W8676: =IF(Main[[#This Row],[Avg_Cost_USD]]<10,"Low", IF(Main[[#This Row],[Avg_Cost_USD]]<=30,"Medium","High")) -> Medium
A8677: 17057397 | B8677: 'Ohana | C8677: 216 | D8677: Orlando | E8677: Disney World Area | F8677: -81.585226 | G8677: 28.405437 | H8677: Hawaiian | I8677: Dollar($) | J8677: No | K8677: No | L8677: No | M8677: No | N8677: 3 | O8677: 1151 | P8677: 45 | Q8677: 4.5 | R8677: 2016 | S8677: 2 | T8677: 15 | U8677: 42415 | V8677: =Main[[#This Row],[Average_Cost_for_two]] * VLOOKUP(Main[[#This Row],[Currency]],'Currency'!A:B,2,FALSE) -> 45 | W8677: =IF(Main[[#This Row],[Avg_Cost_USD]]<10,"Low", IF(Main[[#This Row],[Avg_Cost_USD]]<=30,"Medium","High")) -> High
A8678: 3393 | B8678: Parikrama - The Revolving Restaurant | C8678: 1 | D8678: New Delhi | E8678: Connaught Place | F8678: 77.222638 | G8678: 28.628453 | H8678: North Indian, Chinese, Mughlai | I8678: Indian Rupees(Rs.) | J8678: No | K8678: No | L8678: No | M8678: No | N8678: 4 | O8678: 2689 | P8678: 2400 | Q8678: 3.8 | R8678: 2014 | S8678: 7 | T8678: 8 | U8678: 41828 | V8678: =Main[[#This Row],[Average_Cost_for_two]] * VLOOKUP(Main[[#This Row],[Currency]],'Currency'!A:B,2,FALSE) -> 28.8 | W8678: =IF(Main[[#This Row],[Avg_Cost_USD]]<10,"Low", IF(Main[[#This Row],[Avg_Cost_USD]]<=30,"Medium","High")) -> Medium
A8679: 17284302 | B8679: El Vaquero Mexican Restaurant | C8679: 216 | D8679: Albany | E8679: Albany | F8679: -84.2194 | G8679: 31.6158 | H8679: Mexican | I8679: Dollar($) | J8679: No | K8679: No | L8679: No | M8679: No | N8679: 1 | O8679: 45 | P8679: 0 | Q8679: 3.4 | R8679: 2016 | S8679: 1 | T8679: 23 | U8679: 42392 | V8679: =Main[[#This Row],[Average_Cost_for_two]] * VLOOKUP(Main[[#This Row],[Currency]],'Currency'!A:B,2,FALSE) -> 0 | W8679: =IF(Main[[#This Row],[Avg_Cost_USD]]<10,"Low", IF(Main[[#This Row],[Avg_Cost_USD]]<=30,"Medium","High")) -> Low
A8680: 3288 | B8680: Shanghai Bar & Lounge - The Bristol Hotel | C8680: 1 | D8680: Gurgaon | E8680: The Bristol Hotel, DLF Phase 1 | F8680: 77.09232 | G8680: 28.479998 | H8680: Finger Food | I8680: Indian Rupees(Rs.) | J8680: Yes | K8680: No | L8680: No | M8680: No | N8680: 4 | O8680: 17 | P8680: 2400 | Q8680: 3 | R8680: 2017 | S8680: 10 | T8680: 26 | U8680: 43034 | V8680: =Main[[#This Row],[Average_Cost_for_two]] * VLOOKUP(Main[[#This Row],[Currency]],'Currency'!A:B,2,FALSE) -> 28.8 | W8680: =IF(Main[[#This Row],[Avg_Cost_USD]]<10,"Low", IF(Main[[#This Row],[Avg_Cost_USD]]<=30,"Medium","High")) -> Medium
A8681: 3237 | B8681: Club Ice Cube | C8681: 1 | D8681: Noida | E8681: The Great India Place, Sector 38 | F8681: 77.326475 | G8681: 28.568067 | H8681: North Indian, Continental, Chinese | I8681: Indian Rupees(Rs.) | J8681: Yes | K8681: No | L8681: No | M8681: No | N8681: 4 | O8681: 230 | P8681: 2400 | Q8681: 2 | R8681: 2011 | S8681: 4 | T8681: 16 | U8681: 40649 | V8681: =Main[[#This Row],[Average_Cost_for_two]] * VLOOKUP(Main[[#This Row],[Currency]],'Currency'!A:B,2,FALSE) -> 28.8 | W8681: =IF(Main[[#This Row],[Avg_Cost_USD]]<10,"Low", IF(Main[[#This Row],[Avg_Cost_USD]]<=30,"Medium","High")) -> Medium
... A8694: 17058534 | B8694: Earl of Sandwich | C8694: 216 | D8694: Orlando | E8694: Disney: Downtown Disney | F8694: -81.514608 | G8694: 28.372858 | H8694: American, Sandwich, Salad | I8694: Dollar($) | J8694: No | K8694: No | L8694: No | M8694: No | N8694: 3 | O8694: 1341 | P8694: 35 | Q8694: 4.7 | R8694: 2015 | S8694: 11 | T8694: 17 | U8694: 42325 | V8694: =Main[[#This Row],[Average_Cost_for_two]] * VLOOKUP(Main[[#This Row],[Currency]],'Currency'!A:B,2,FALSE) -> 35 | W8694: =IF(Main[[#This Row],[Avg_Cost_USD]]<10,"Low", IF(Main[[#This Row],[Avg_Cost_USD]]<=30,"Medium","High")) -> High
A8695: 17284105 | B8695: Cookie Shoppe | C8695: 216 | D8695: Albany | E8695: Albany | F8695: -84.154 | G8695: 31.5772 | I8695: Dollar($) | J8695: No | K8695: No | L8695: No | M8695: No | N8695: 1 | O8695: 34 | P8695: 0 | Q8695: 3.4 | R8695: 2011 | S8695: 10 | T8695: 20 | U8695: 40836 | V8695: =Main[[#This Row],[Average_Cost_for_two]] * VLOOKUP(Main[[#This Row],[Currency]],'Currency'!A:B,2,FALSE) -> 0 | W8695: =IF(Main[[#This Row],[Avg_Cost_USD]]<10,"Low", IF(Main[[#This Row],[Avg_Cost_USD]]<=30,"Medium","High")) -> Low
A8696: 17678231 | B8696: Beijing Cafe | C8696: 216 | D8696: Valdosta | E8696: Valdosta | F8696: -83.318554 | G8696: 30.841892 | H8696: Asian, Chinese, Thai | I8696: Dollar($) | J8696: No | K8696: No | L8696: No | M8696: No | N8696: 3 | O8696: 185 | P8696: 35 | Q8696: 3.8 | R8696: 2011 | S8696: 10 | T8696: 22 | U8696: 40838 | V8696: =Main[[#This Row],[Average_Cost_for_two]] * VLOOKUP(Main[[#This Row],[Currency]],'Currency'!A:B,2,FALSE) -> 35 | W8696: =IF(Main[[#This Row],[Avg_Cost_USD]]<10,"Low", IF(Main[[#This Row],[Avg_Cost_USD]]<=30,"Medium","High")) -> High
A8697: 17295028 | B8697: Manuel's Bread Cafe | C8697: 216 | D8697: Augusta | E8697: Augusta | F8697: -81.965571 | G8697: 33.481779 | H8697: Breakfast, French | I8697: Dollar($) | J8697: No | K8697: No | L8697: No | M8697: No | N8697: 3 | O8697: 332 | P8697: 40 | Q8697: 3.8 | R8697: 2012 | S8697: 9 | T8697: 13 | U8697: 41165 | V8697: =Main[[#This Row],[Average_Cost_for_two]] * VLOOKUP(Main[[#This Row],[Currency]],'Currency'!A:B,2,FALSE) -> 40 | W8697: =IF(Main[[#This Row],[Avg_Cost_USD]]<10,"Low", IF(Main[[#This Row],[Avg_Cost_USD]]<=30,"Medium","High")) -> High
A8698: 17316743 | B8698: Graze | C8698: 216 | D8698: Cedar Rapids/Iowa City | E8698: Iowa City | F8698: -91.534302 | G8698: 41.658691 | H8698: American, International, Sushi | I8698: Dollar($) | J8698: No | K8698: No | L8698: No | M8698: No | N8698: 3 | O8698: 220 | P8698: 40 | Q8698: 3.8 | R8698: 2015 | S8698: 9 | T8698: 27 | U8698: 42274 | V8698: =Main[[#This Row],[Average_Cost_for_two]] * VLOOKUP(Main[[#This Row],[Currency]],'Currency'!A:B,2,FALSE) -> 40 | W8698: =IF(Main[[#This Row],[Avg_Cost_USD]]<10,"Low", IF(Main[[#This Row],[Avg_Cost_USD]]<=30,"Medium","High")) -> High
A8699: 17330185 | B8699: Fuji Japanese Steak House | C8699: 216 | D8699: Columbus | E8699: Columbus | F8699: -84.954984 | G8699: 32.53822 | H8699: Japanese, Steak | I8699: Dollar($) | J8699: No | K8699: No | L8699: No | M8699: No | N8699: 3 | O8699: 247 | P8699: 40 | Q8699: 3.9 | R8699: 2011 | S8699: 9 | T8699: 7 | U8699: 40793 | V8699: =Main[[#This Row],[Average_Cost_for_two]] * VLOOKUP(Main[[#This Row],[Currency]],'Currency'!A:B,2,FALSE) -> 40 | W8699: =IF(Main[[#This Row],[Avg_Cost_USD]]<10,"Low", IF(Main[[#This Row],[Avg_Cost_USD]]<=30,"Medium","High")) -> High
A8700: 17258350 | B8700: Flying Mango | C8700: 216 | D8700: Des Moines | E8700: Beaverdale | F8700: -93.677638 | G8700: 41.614965 | H8700: BBQ, Caribbean, Cajun | I8700: Dollar($) | J8700: No | K8700: No | L8700: No | M8700: No | N8700: 3 | O8700: 674 | P8700: 40 | Q8700: 4.5 | R8700: 2016 | S8700: 9 | T8700: 20 | U8700: 42633 | V8700: =Main[[#This Row],[Average_Cost_for_two]] * VLOOKUP(Main[[#This Row],[Currency]],'Currency'!A:B,2,FALSE) -> 40 | W8700: =IF(Main[[#This Row],[Avg_Cost_USD]]<10,"Low", IF(Main[[#This Row],[Avg_Cost_USD]]<=30,"Medium","High")) -> High
A8701: 17259200 | B8701: Waterfront Seafood Market | C8701: 216 | D8701: Des Moines | E8701: West Des Moines | F8701: -93.744198 | G8701: 41.599177 | H8701: Seafood, Sushi | I8701: Dollar($) | J8701: No | K8701: No | L8701: No | M8701: No | N8701: 3 | O8701: 530 | P8701: 40 | Q8701: 4.2 | R8701: 2010 | S8701: 9 | T8701: 21 | U8701: 40442 | V8701: =Main[[#This Row],[Average_Cost_for_two]] * VLOOKUP(Main[[#This Row],[Currency]],'Currency'!A:B,2,FALSE) -> 40 | W8701: =IF(Main[[#This Row],[Avg_Cost_USD]]<10,"Low", IF(Main[[#This Row],[Avg_Cost_USD]]<=30,"Medium","High")) -> High
A8702: 17342770 | B8702: L. May Eatery | C8702: 216 | D8702: Dubuque | E8702: Dubuque | F8702: -90.668164 | G8702: 42.503075 | H8702: International, Pizza | I8702: Dollar($) | J8702: No | K8702: No | L8702: No | M8702: No | N8702: 3 | O8702: 198 | P8702: 40 | Q8702: 3.8 | R8702: 2011 | S8702: 9 | T8702: 8 | U8702: 40794 | V8702: =Main[[#This Row],[Average_Cost_for_two]] * VLOOKUP(Main[[#This Row],[Currency]],'Currency'!A:B,2,FALSE) -> 40 | W8702: =IF(Main[[#This Row],[Avg_Cost_USD]]<10,"Low", IF(Main[[#This Row],[Avg_Cost_USD]]<=30,"Medium","High")) -> High
A8703: 17374552 | B8703: Corkscrew Cafe | C8703: 216 | D8703: Gainesville | E8703: Dahlonega | F8703: -83.9858 | G8703: 34.5318 | I8703: Dollar($) | J8703: No | K8703: No | L8703: No | M8703: No | N8703: 3 | O8703: 209 | P8703: 40 | Q8703: 3.9 | R8703: 2016 | S8703: 9 | T8703: 3 | U8703: 42616 | V8703: =Main[[#This Row],[Average_Cost_for_two]] * VLOOKUP(Main[[#This Row],[Currency]],'Currency'!A:B,2,FALSE) -> 40 | W8703: =IF(Main[[#This Row],[Avg_Cost_USD]]<10,"Low", IF(Main[[#This Row],[Avg_Cost_USD]]<=30,"Medium","High")) -> High
A8704: 17057925 | B8704: Cafí© Tu Tu Tango | C8704: 216 | D8704: Orlando | E8704: I-Drive/Universal | F8704: -81.469986 | G8704: 28.440344 | H8704: New American, Tapas | I8704: Dollar($) | J8704: No | K8704: No | L8704: No | M8704: No | N8704: 3 | O8704: 1293 | P8704: 40 | Q8704: 4.6 | R8704: 2012 | S8704: 9 | T8704: 12 | U8704: 41164 | V8704: =Main[[#This Row],[Average_Cost_for_two]] * VLOOKUP(Main[[#This Row],[Currency]],'Currency'!A:B,2,FALSE) -> 40 | W8704: =IF(Main[[#This Row],[Avg_Cost_USD]]<10,"Low", IF(Main[[#This Row],[Avg_Cost_USD]]<=30,"Medium","High")) -> High
A8705: 17057797 | B8705: Bosphorous Turkish Cuisine | C8705: 216 | D8705: Orlando | E8705: Winter Park | F8705: -81.350834 | G8705: 28.597627 | H8705: Mediterranean, Turkish | I8705: Dollar($) | J8705: No | K8705: No | L8705: No | M8705: No | N8705: 3 | O8705: 568 | P8705: 40 | Q8705: 4.2 | R8705: 2011 | S8705: 9 | T8705: 13 | U8705: 40799 | V8705: =Main[[#This Row],[Average_Cost_for_two]] * VLOOKUP(Main[[#This Row],[Currency]],'Currency'!A:B,2,FALSE) -> 40 | W8705: =IF(Main[[#This Row],[Avg_Cost_USD]]<10,"Low", IF(Main[[#This Row],[Avg_Cost_USD]]<=30,"Medium","High")) -> High
A8706: 17579992 | B8706: Dharma Blue | C8706: 216 | D8706: Pensacola | E8706: Pensacola | F8706: -87.2092 | G8706: 30.4101 | H8706: Seafood, Sushi | I8706: Dollar($) | J8706: No | K8706: No | L8706: No | M8706: No | N8706: 3 | O8706: 669 | P8706: 40 | Q8706: 4.1 | R8706: 2012 | S8706: 9 | T8706: 2 | U8706: 41154 | V8706: =Main[[#This Row],[Average_Cost_for_two]] * VLOOKUP(Main[[#This Row],[Currency]],'Currency'!A:B,2,FALSE) -> 40 | W8706: =IF(Main[[#This Row],[Avg_Cost_USD]]<10,"Low", IF(Main[[#This Row],[Avg_Cost_USD]]<=30,"Medium","High")) -> High
A8707: 17145408 | B8707: Monkeypod Kitchen by Merriman | C8707: 216 | D8707: Rest of Hawaii | E8707: Kihei | F8707: -156.43095 | G8707: 20.688375 | H8707: Burger | I8707: Dollar($) | J8707: No | K8707: No | L8707: No | M8707: No | N8707: 3 | O8707: 485 | P8707: 40 | Q8707: 4.2 | R8707: 2018 | S8707: 9 | T8707: 17 | U8707: 43360 | V8707: =Main[[#This Row],[Average_Cost_for_two]] * VLOOKUP(Main[[#This Row],[Currency]],'Currency'!A:B,2,FALSE) -> 40 | W8707: =IF(Main[[#This Row],[Avg_Cost_USD]]<10,"Low", IF(Main[[#This Row],[Avg_Cost_USD]]<=30,"Medium","High")) -> High
A8708: 17142297 | B8708: Hula Grill | C8708: 216 | D8708: Rest of Hawaii | E8708: Lahaina | F8708: -156.69382 | G8708: 20.921347 | H8708: Hawaiian, Seafood, Steak | I8708: Dollar($) | J8708: No | K8708: No | L8708: No | M8708: No | N8708: 3 | O8708: 1056 | P8708: 40 | Q8708: 4.3 | R8708: 2010 | S8708: 9 | T8708: 16 | U8708: 40437 | V8708: =Main[[#This Row],[Average_Cost_for_two]] * VLOOKUP(Main[[#This Row],[Currency]],'Currency'!A:B,2,FALSE) -> 40 | W8708: =IF(Main[[#This Row],[Avg_Cost_USD]]<10,"Low", IF(Main[[#This Row],[Avg_Cost_USD]]<=30,"Medium","High")) -> High
A8709: 17143950 | B8709: Yard House | C8709: 216 | D8709: Rest of Hawaii | E8709: Waikiki | F8709: -157.83125 | G8709: 21.279495 | H8709: American, Asian, Burger | I8709: Dollar($) | J8709: No | K8709: No | L8709: No | M8709: No | N8709: 3 | O8709: 1078 | P8709: 40 | Q8709: 4.6 | R8709: 2017 | S8709: 9 | T8709: 4 | U8709: 42982 | V8709: =Main[[#This Row],[Average_Cost_for_two]] * VLOOKUP(Main[[#This Row],[Currency]],'Currency'!A:B,2,FALSE) -> 40 | W8709: =IF(Main[[#This Row],[Avg_Cost_USD]]<10,"Low", IF(Main[[#This Row],[Avg_Cost_USD]]<=30,"Medium","High")) -> High
A8710: 17621763 | B8710: Fuji Bay Japanese Restaurant | C8710: 216 | D8710: Sioux City | E8710: Sioux City | F8710: -96.4046 | G8710: 42.4965 | H8710: Japanese, Sushi | I8710: Dollar($) | J8710: No | K8710: No | L8710: No | M8710: No | N8710: 3 | O8710: 129 | P8710: 40 | Q8710: 3.7 | R8710: 2013 | S8710: 9 | T8710: 23 | U8710: 41540 | V8710: =Main[[#This Row],[Average_Cost_for_two]] * VLOOKUP(Main[[#This Row],[Currency]],'Currency'!A:B,2,FALSE) -> 40 | W8710: =IF(Main[[#This Row],[Avg_Cost_USD]]<10,"Low", IF(Main[[#This Row],[Avg_Cost_USD]]<=30,"Medium","High")) -> High
A8711: 17621960 | B8711: Tokyo Japanese Steakhouse & Sushi Bar | C8711: 216 | D8711: Sioux City | E8711: Sioux City | F8711: -96.349464 | G8711: 42.440592 | H8711: Japanese, Steak, Sushi | I8711: Dollar($) | J8711: No | K8711: No | L8711: No | M8711: No | N8711: 3 | O8711: 239 | P8711: 40 | Q8711: 3.9 | R8711: 2018 | S8711: 9 | T8711: 27 | U8711: 43370 | V8711: =Main[[#This Row],[Average_Cost_for_two]] * VLOOKUP(Main[[#This Row],[Currency]],'Currency'!A:B,2,FALSE) -> 40 | W8711: =IF(Main[[#This Row],[Avg_Cost_USD]]<10,"Low", IF(Main[[#This Row],[Avg_Cost_USD]]<=30,"Medium","High")) -> High
A8712: 17621755 | B8712: El Fredo Pizza | C8712: 216 | D8712: Sioux City | E8712: Sioux City | F8712: -96.4204 | G8712: 42.5106 | H8712: Pizza | I8712: Dollar($) | J8712: No | K8712: No | L8712: No | M8712: No | N8712: 3 | O8712: 280 | P8712: 40 | Q8712: 4 | R8712: 2015 | S8712: 9 | T8712: 24 | U8712: 42271 | V8712: =Main[[#This Row],[Average_Cost_for_two]] * VLOOKUP(Main[[#This Row],[Currency]],'Currency'!A:B,2,FALSE) -> 40 | W8712: =IF(Main[[#This Row],[Avg_Cost_USD]]<10,"Low", IF(Main[[#This Row],[Avg_Cost_USD]]<=30,"Medium","High")) -> High
A8713: 17293273 | B8713: La Dolce Vita Ristorante | C8713: 216 | D8713: Athens | E8713: Athens | F8713: -83.4075 | G8713: 33.9584 | H8713: Italian | I8713: Dollar($) | J8713: No | K8713: No | L8713: No | M8713: No | N8713: 3 | O8713: 464 | P8713: 40 | Q8713: 4.1 | R8713: 2018 | S8713: 8 | T8713: 28 | U8713: 43340 | V8713: =Main[[#This Row],[Average_Cost_for_two]] * VLOOKUP(Main[[#This Row],[Currency]],'Currency'!A:B,2,FALSE) -> 40 | W8713: =IF(Main[[#This Row],[Avg_Cost_USD]]<10,"Low", IF(Main[[#This Row],[Avg_Cost_USD]]<=30,"Medium","High")) -> High
A8714: 17303787 | B8714: Mai Thai Restaurant | C8714: 216 | D8714: Boise | E8714: Boise | F8714: -116.2021 | G8714: 43.6162 | H8714: Sushi, Thai | I8714: Dollar($) | J8714: No | K8714: No | L8714: No | M8714: No | N8714: 3 | O8714: 340 | P8714: 40 | Q8714: 4 | R8714: 2016 | S8714: 8 | T8714: 2 | U8714: 42584 | V8714: =Main[[#This Row],[Average_Cost_for_two]] * VLOOKUP(Main[[#This Row],[Currency]],'Currency'!A:B,2,FALSE) -> 40 | W8714: =IF(Main[[#This Row],[Avg_Cost_USD]]<10,"Low", IF(Main[[#This Row],[Avg_Cost_USD]]<=30,"Medium","High")) -> High
A8715: 17316018 | B8715: Granite City Food & Brewery | C8715: 216 | D8715: Cedar Rapids/Iowa City | E8715: Cedar Rapids | F8715: -91.6224 | G8715: 42.0249 | H8715: American, Breakfast, Burger | I8715: Dollar($) | J8715: No | K8715: No | L8715: No | M8715: No | N8715: 3 | O8715: 429 | P8715: 40 | Q8715: 4.1 | R8715: 2012 | S8715: 8 | T8715: 20 | U8715: 41141 | V8715: =Main[[#This Row],[Average_Cost_for_two]] * VLOOKUP(Main[[#This Row],[Currency]],'Currency'!A:B,2,FALSE) -> 40 | W8715: =IF(Main[[#This Row],[Avg_Cost_USD]]<10,"Low", IF(Main[[#This Row],[Avg_Cost_USD]]<=30,"Medium","High")) -> High
... A8765: 17316381 | B8765: Atlas World Grill | C8765: 216 | D8765: Cedar Rapids/Iowa City | E8765: Iowa City | F8765: -91.5341 | G8765: 41.661 | H8765: International | I8765: Dollar($) | J8765: No | K8765: No | L8765: No | M8765: No | N8765: 3 | O8765: 428 | P8765: 40 | Q8765: 4.3 | R8765: 2014 | S8765: 1 | T8765: 8 | U8765: 41647 | V8765: =Main[[#This Row],[Average_Cost_for_two]] * VLOOKUP(Main[[#This Row],[Currency]],'Currency'!A:B,2,FALSE) -> 40 | W8765: =IF(Main[[#This Row],[Avg_Cost_USD]]<10,"Low", IF(Main[[#This Row],[Avg_Cost_USD]]<=30,"Medium","High")) -> High
A8766: 17501439 | B8766: Dovetail | C8766: 216 | D8766: Macon | E8766: Macon | F8766: -83.627979 | G8766: 32.83641 | I8766: Dollar($) | J8766: No | K8766: No | L8766: No | M8766: No | N8766: 3 | O8766: 102 | P8766: 40 | Q8766: 3.8 | R8766: 2014 | S8766: 1 | T8766: 28 | U8766: 41667 | V8766: =Main[[#This Row],[Average_Cost_for_two]] * VLOOKUP(Main[[#This Row],[Currency]],'Currency'!A:B,2,FALSE) -> 40 | W8766: =IF(Main[[#This Row],[Avg_Cost_USD]]<10,"Low", IF(Main[[#This Row],[Avg_Cost_USD]]<=30,"Medium","High")) -> High
A8767: 17061231 | B8767: The Ravenous Pig | C8767: 216 | D8767: Orlando | E8767: Winter Park | F8767: -81.356024 | G8767: 28.593297 | H8767: Pub Food | I8767: Dollar($) | J8767: No | K8767: No | L8767: No | M8767: No | N8767: 3 | O8767: 1998 | P8767: 40 | Q8767: 4.4 | R8767: 2012 | S8767: 1 | T8767: 15 | U8767: 40923 | V8767: =Main[[#This Row],[Average_Cost_for_two]] * VLOOKUP(Main[[#This Row],[Currency]],'Currency'!A:B,2,FALSE) -> 40 | W8767: =IF(Main[[#This Row],[Avg_Cost_USD]]<10,"Low", IF(Main[[#This Row],[Avg_Cost_USD]]<=30,"Medium","High")) -> High
A8768: 17580412 | B8768: Carrabba's Italian Grill | C8768: 216 | D8768: Pensacola | E8768: Pensacola | F8768: -87.205855 | G8768: 30.417318 | H8768: Italian, Pizza, Seafood | I8768: Dollar($) | J8768: No | K8768: No | L8768: No | M8768: No | N8768: 3 | O8768: 292 | P8768: 40 | Q8768: 3.7 | R8768: 2011 | S8768: 1 | T8768: 23 | U8768: 40566 | V8768: =Main[[#This Row],[Average_Cost_for_two]] * VLOOKUP(Main[[#This Row],[Currency]],'Currency'!A:B,2,FALSE) -> 40 | W8768: =IF(Main[[#This Row],[Avg_Cost_USD]]<10,"Low", IF(Main[[#This Row],[Avg_Cost_USD]]<=30,"Medium","High")) -> High
A8769: 17697398 | B8769: Sakura | C8769: 216 | D8769: Waterloo | E8769: Cedar Falls | F8769: -92.426215 | G8769: 42.51259 | H8769: Japanese, Sushi | I8769: Dollar($) | J8769: No | K8769: No | L8769: No | M8769: No | N8769: 3 | O8769: 175 | P8769: 40 | Q8769: 3.8 | R8769: 2011 | S8769: 1 | T8769: 26 | U8769: 40569 | V8769: =Main[[#This Row],[Average_Cost_for_two]] * VLOOKUP(Main[[#This Row],[Currency]],'Currency'!A:B,2,FALSE) -> 40 | W8769: =IF(Main[[#This Row],[Avg_Cost_USD]]<10,"Low", IF(Main[[#This Row],[Avg_Cost_USD]]<=30,"Medium","High")) -> High
A8770: 17294607 | B8770: Rae's Coastal Cafe | C8770: 216 | D8770: Augusta | E8770: Augusta | F8770: -82.0698 | G8770: 33.4791 | H8770: American, Caribbean, Seafood | I8770: Dollar($) | J8770: No | K8770: No | L8770: No | M8770: No | N8770: 3 | O8770: 548 | P8770: 40 | Q8770: 4.9 | R8770: 2010 | S8770: 12 | T8770: 26 | U8770: 40538 | V8770: =Main[[#This Row],[Average_Cost_for_two]] * VLOOKUP(Main[[#This Row],[Currency]],'Currency'!A:B,2,FALSE) -> 40 | W8770: =IF(Main[[#This Row],[Avg_Cost_USD]]<10,"Low", IF(Main[[#This Row],[Avg_Cost_USD]]<=30,"Medium","High")) -> High
A8771: 17334217 | B8771: Fuji Japanese Steakhouse | C8771: 216 | D8771: Dalton | E8771: Dalton | F8771: -84.992342 | G8771: 34.759551 | H8771: Japanese, Sushi | I8771: Dollar($) | J8771: No | K8771: No | L8771: No | M8771: No | N8771: 3 | O8771: 145 | P8771: 40 | Q8771: 3.8 | R8771: 2012 | S8771: 12 | T8771: 13 | U8771: 41256 | V8771: =Main[[#This Row],[Average_Cost_for_two]] * VLOOKUP(Main[[#This Row],[Currency]],'Currency'!A:B,2,FALSE) -> 40 | W8771: =IF(Main[[#This Row],[Avg_Cost_USD]]<10,"Low", IF(Main[[#This Row],[Avg_Cost_USD]]<=30,"Medium","High")) -> High
A8772: 17335168 | B8772: Osaka | C8772: 216 | D8772: Davenport | E8772: Davenport | F8772: -90.515175 | G8772: 41.570997 | H8772: Japanese, Sushi | I8772: Dollar($) | J8772: No | K8772: No | L8772: No | M8772: No | N8772: 3 | O8772: 141 | P8772: 40 | Q8772: 4.2 | R8772: 2015 | S8772: 12 | T8772: 23 | U8772: 42361 | V8772: =Main[[#This Row],[Average_Cost_for_two]] * VLOOKUP(Main[[#This Row],[Currency]],'Currency'!A:B,2,FALSE) -> 40 | W8772: =IF(Main[[#This Row],[Avg_Cost_USD]]<10,"Low", IF(Main[[#This Row],[Avg_Cost_USD]]<=30,"Medium","High")) -> High
A8773: 17059060 | B8773: Hillstone | C8773: 216 | D8773: Orlando | E8773: Winter Park | F8773: -81.36526 | G8773: 28.596682 | I8773: Dollar($) | J8773: No | K8773: No | L8773: No | M8773: No | N8773: 3 | O8773: 1158 | P8773: 40 | Q8773: 4.4 | R8773: 2015 | S8773: 12 | T8773: 3 | U8773: 42341 | V8773: =Main[[#This Row],[Average_Cost_for_two]] * VLOOKUP(Main[[#This Row],[Currency]],'Currency'!A:B,2,FALSE) -> 40 | W8773: =IF(Main[[#This Row],[Avg_Cost_USD]]<10,"Low", IF(Main[[#This Row],[Avg_Cost_USD]]<=30,"Medium","High")) -> High
A8774: 17580142 | B8774: McGuire's Irish Pub & Brewery | C8774: 216 | D8774: Pensacola | E8774: Pensacola | F8774: -87.2027 | G8774: 30.4179 | H8774: Burger, Bar Food, Steak | I8774: Dollar($) | J8774: No | K8774: No | L8774: No | M8774: No | N8774: 3 | O8774: 2238 | P8774: 40 | Q8774: 4.9 | R8774: 2018 | S8774: 12 | T8774: 2 | U8774: 43436 | V8774: =Main[[#This Row],[Average_Cost_for_two]] * VLOOKUP(Main[[#This Row],[Currency]],'Currency'!A:B,2,FALSE) -> 40 | W8774: =IF(Main[[#This Row],[Avg_Cost_USD]]<10,"Low", IF(Main[[#This Row],[Avg_Cost_USD]]<=30,"Medium","High")) -> High
A8775: 17616487 | B8775: Green Truck Pub | C8775: 216 | D8775: Savannah | E8775: Savannah | F8775: -81.096647 | G8775: 32.052858 | H8775: Burger | I8775: Dollar($) | J8775: No | K8775: No | L8775: No | M8775: No | N8775: 3 | O8775: 906 | P8775: 40 | Q8775: 4.7 | R8775: 2012 | S8775: 12 | T8775: 26 | U8775: 41269 | V8775: =Main[[#This Row],[Average_Cost_for_two]] * VLOOKUP(Main[[#This Row],[Currency]],'Currency'!A:B,2,FALSE) -> 40 | W8775: =IF(Main[[#This Row],[Avg_Cost_USD]]<10,"Low", IF(Main[[#This Row],[Avg_Cost_USD]]<=30,"Medium","High")) -> High
A8776: 17099856 | B8776: Datz | C8776: 216 | D8776: Tampa Bay | E8776: Palma Ceia | F8776: -82.493281 | G8776: 27.921931 | H8776: Desserts, Bar Food | I8776: Dollar($) | J8776: No | K8776: No | L8776: No | M8776: No | N8776: 3 | O8776: 3074 | P8776: 40 | Q8776: 4.7 | R8776: 2016 | S8776: 12 | T8776: 23 | U8776: 42727 | V8776: =Main[[#This Row],[Average_Cost_for_two]] * VLOOKUP(Main[[#This Row],[Currency]],'Currency'!A:B,2,FALSE) -> 40 | W8776: =IF(Main[[#This Row],[Avg_Cost_USD]]<10,"Low", IF(Main[[#This Row],[Avg_Cost_USD]]<=30,"Medium","High")) -> High
A8777: 17697386 | B8777: Galleria de Paco | C8777: 216 | D8777: Waterloo | E8777: Waterloo | F8777: -92.339721 | G8777: 42.494908 | H8777: American | I8777: Dollar($) | J8777: No | K8777: No | L8777: No | M8777: No | N8777: 3 | O8777: 86 | P8777: 40 | Q8777: 3.6 | R8777: 2017 | S8777: 12 | T8777: 10 | U8777: 43079 | V8777: =Main[[#This Row],[Average_Cost_for_two]] * VLOOKUP(Main[[#This Row],[Currency]],'Currency'!A:B,2,FALSE) -> 40 | W8777: =IF(Main[[#This Row],[Avg_Cost_USD]]<10,"Low", IF(Main[[#This Row],[Avg_Cost_USD]]<=30,"Medium","High")) -> High
A8778: 17293281 | B8778: Last Resort Grill | C8778: 216 | D8778: Athens | E8778: Athens | F8778: -83.378273 | G8778: 33.957999 | H8778: American, Southern, Southwestern | I8778: Dollar($) | J8778: No | K8778: No | L8778: No | M8778: No | N8778: 3 | O8778: 1821 | P8778: 40 | Q8778: 4.5 | R8778: 2017 | S8778: 11 | T8778: 7 | U8778: 43046 | V8778: =Main[[#This Row],[Average_Cost_for_two]] * VLOOKUP(Main[[#This Row],[Currency]],'Currency'!A:B,2,FALSE) -> 40 | W8778: =IF(Main[[#This Row],[Avg_Cost_USD]]<10,"Low", IF(Main[[#This Row],[Avg_Cost_USD]]<=30,"Medium","High")) -> High
A8779: 17294556 | B8779: Miyabi Kyoto Japanese Steak House | C8779: 216 | D8779: Augusta | E8779: Augusta | F8779: -82.0865 | G8779: 33.4721 | H8779: Chinese, Steak | I8779: Dollar($) | J8779: No | K8779: No | L8779: No | M8779: No | N8779: 3 | O8779: 717 | P8779: 40 | Q8779: 4.6 | R8779: 2012 | S8779: 11 | T8779: 8 | U8779: 41221 | V8779: =Main[[#This Row],[Average_Cost_for_two]] * VLOOKUP(Main[[#This Row],[Currency]],'Currency'!A:B,2,FALSE) -> 40 | W8779: =IF(Main[[#This Row],[Avg_Cost_USD]]<10,"Low", IF(Main[[#This Row],[Avg_Cost_USD]]<=30,"Medium","High")) -> High
A8780: 17316416 | B8780: Devotay | C8780: 216 | D8780: Cedar Rapids/Iowa City | E8780: Iowa City | F8780: -91.5318 | G8780: 41.6625 | H8780: Mediterranean, Tapas, Vegetarian | I8780: Dollar($) | J8780: No | K8780: No | L8780: No | M8780: No | N8780: 3 | O8780: 380 | P8780: 40 | Q8780: 4 | R8780: 2013 | S8780: 11 | T8780: 8 | U8780: 41586 | V8780: =Main[[#This Row],[Average_Cost_for_two]] * VLOOKUP(Main[[#This Row],[Currency]],'Currency'!A:B,2,FALSE) -> 40 | W8780: =IF(Main[[#This Row],[Avg_Cost_USD]]<10,"Low", IF(Main[[#This Row],[Avg_Cost_USD]]<=30,"Medium","High")) -> High
A8781: 17330311 | B8781: Meritage | C8781: 216 | D8781: Columbus | E8781: Columbus | F8781: -84.992093 | G8781: 32.466158 | H8781: American, Tapas | I8781: Dollar($) | J8781: No | K8781: No | L8781: No | M8781: No | N8781: 3 | O8781: 302 | P8781: 40 | Q8781: 4.1 | R8781: 2011 | S8781: 11 | T8781: 1 | U8781: 40848 | V8781: =Main[[#This Row],[Average_Cost_for_two]] * VLOOKUP(Main[[#This Row],[Currency]],'Currency'!A:B,2,FALSE) -> 40 | W8781: =IF(Main[[#This Row],[Avg_Cost_USD]]<10,"Low", IF(Main[[#This Row],[Avg_Cost_USD]]<=30,"Medium","High")) -> High
A8782: 17330628 | B8782: Wood Stone | C8782: 216 | D8782: Columbus | E8782: Columbus | F8782: -84.963201 | G8782: 32.527217 | H8782: Italian, Mediterranean, Pizza | I8782: Dollar($) | J8782: No | K8782: No | L8782: No | M8782: No | N8782: 3 | O8782: 264 | P8782: 40 | Q8782: 4 | R8782: 2010 | S8782: 11 | T8782: 4 | U8782: 40486 | V8782: =Main[[#This Row],[Average_Cost_for_two]] * VLOOKUP(Main[[#This Row],[Currency]],'Currency'!A:B,2,FALSE) -> 40 | W8782: =IF(Main[[#This Row],[Avg_Cost_USD]]<10,"Low", IF(Main[[#This Row],[Avg_Cost_USD]]<=30,"Medium","High")) -> High
A8783: 17335195 | B8783: Red Ginger Sushi, Grill & Bar | C8783: 216 | D8783: Davenport | E8783: Bettendorf | F8783: -90.522479 | G8783: 41.53845 | H8783: Sushi, Teriyaki | I8783: Dollar($) | J8783: No | K8783: No | L8783: No | M8783: No | N8783: 3 | O8783: 208 | P8783: 40 | Q8783: 4.5 | R8783: 2016 | S8783: 11 | T8783: 5 | U8783: 42679 | V8783: =Main[[#This Row],[Average_Cost_for_two]] * VLOOKUP(Main[[#This Row],[Currency]],'Currency'!A:B,2,FALSE) -> 40 | W8783: =IF(Main[[#This Row],[Avg_Cost_USD]]<10,"Low", IF(Main[[#This Row],[Avg_Cost_USD]]<=30,"Medium","High")) -> High
A8784: 17501279 | B8784: Bonefish Grill | C8784: 216 | D8784: Macon | E8784: Macon | F8784: -83.713978 | G8784: 32.929278 | H8784: American, Seafood | I8784: Dollar($) | J8784: No | K8784: No | L8784: No | M8784: No | N8784: 3 | O8784: 293 | P8784: 40 | Q8784: 4.1 | R8784: 2011 | S8784: 11 | T8784: 15 | U8784: 40862 | V8784: =Main[[#This Row],[Average_Cost_for_two]] * VLOOKUP(Main[[#This Row],[Currency]],'Currency'!A:B,2,FALSE) -> 40 | W8784: =IF(Main[[#This Row],[Avg_Cost_USD]]<10,"Low", IF(Main[[#This Row],[Avg_Cost_USD]]<=30,"Medium","High")) -> High
A8785: 17580408 | B8785: Flounders Chowder House | C8785: 216 | D8785: Pensacola | E8785: Pensacola Beach | F8785: -87.143 | G8785: 30.3359 | H8785: Seafood | I8785: Dollar($) | J8785: No | K8785: No | L8785: No | M8785: No | N8785: 3 | O8785: 724 | P8785: 40 | Q8785: 3.9 | R8785: 2014 | S8785: 11 | T8785: 21 | U8785: 41964 | V8785: =Main[[#This Row],[Average_Cost_for_two]] * VLOOKUP(Main[[#This Row],[Currency]],'Currency'!A:B,2,FALSE) -> 40 | W8785: =IF(Main[[#This Row],[Avg_Cost_USD]]<10,"Low", IF(Main[[#This Row],[Avg_Cost_USD]]<=30,"Medium","High")) -> High
... A8795: 17615979 | B8795: Mrs. Wilkes' Dining Room | C8795: 216 | D8795: Savannah | E8795: Savannah | F8795: -81.0955 | G8795: 32.0727 | H8795: American, Southern | I8795: Dollar($) | J8795: No | K8795: No | L8795: No | M8795: No | N8795: 3 | O8795: 1014 | P8795: 40 | Q8795: 4.5 | R8795: 2015 | S8795: 10 | T8795: 24 | U8795: 42301 | V8795: =Main[[#This Row],[Average_Cost_for_two]] * VLOOKUP(Main[[#This Row],[Currency]],'Currency'!A:B,2,FALSE) -> 40 | W8795: =IF(Main[[#This Row],[Avg_Cost_USD]]<10,"Low", IF(Main[[#This Row],[Avg_Cost_USD]]<=30,"Medium","High")) -> High
A8796: 17284158 | B8796: Jimmie's Hot Dogs | C8796: 216 | D8796: Albany | E8796: Albany | F8796: -84.1534 | G8796: 31.5751 | I8796: Dollar($) | J8796: No | K8796: No | L8796: No | M8796: No | N8796: 1 | O8796: 160 | P8796: 10 | Q8796: 3.9 | R8796: 2013 | S8796: 9 | T8796: 2 | U8796: 41519 | V8796: =Main[[#This Row],[Average_Cost_for_two]] * VLOOKUP(Main[[#This Row],[Currency]],'Currency'!A:B,2,FALSE) -> 10 | W8796: =IF(Main[[#This Row],[Avg_Cost_USD]]<10,"Low", IF(Main[[#This Row],[Avg_Cost_USD]]<=30,"Medium","High")) -> Medium
A8797: 17293880 | B8797: Big City Bread Cafe | C8797: 216 | D8797: Athens | E8797: Athens | F8797: -83.384004 | G8797: 33.959392 | H8797: Breakfast, Sandwich | I8797: Dollar($) | J8797: No | K8797: No | L8797: No | M8797: No | N8797: 1 | O8797: 558 | P8797: 10 | Q8797: 4.3 | R8797: 2012 | S8797: 9 | T8797: 1 | U8797: 41153 | V8797: =Main[[#This Row],[Average_Cost_for_two]] * VLOOKUP(Main[[#This Row],[Currency]],'Currency'!A:B,2,FALSE) -> 10 | W8797: =IF(Main[[#This Row],[Avg_Cost_USD]]<10,"Low", IF(Main[[#This Row],[Avg_Cost_USD]]<=30,"Medium","High")) -> Medium
A8798: 17293229 | B8798: Grit | C8798: 216 | D8798: Athens | E8798: Athens | F8798: -83.381625 | G8798: 33.960112 | H8798: International, Southern, Vegetarian | I8798: Dollar($) | J8798: No | K8798: No | L8798: No | M8798: No | N8798: 1 | O8798: 800 | P8798: 10 | Q8798: 4.2 | R8798: 2013 | S8798: 9 | T8798: 13 | U8798: 41530 | V8798: =Main[[#This Row],[Average_Cost_for_two]] * VLOOKUP(Main[[#This Row],[Currency]],'Currency'!A:B,2,FALSE) -> 10 | W8798: =IF(Main[[#This Row],[Avg_Cost_USD]]<10,"Low", IF(Main[[#This Row],[Avg_Cost_USD]]<=30,"Medium","High")) -> Medium
A8799: 17294300 | B8799: Boll Weevil Cafe | C8799: 216 | D8799: Augusta | E8799: Augusta | F8799: -81.9684 | G8799: 33.474 | H8799: Desserts, Sandwich, Southern | I8799: Dollar($) | J8799: No | K8799: No | L8799: No | M8799: No | N8799: 1 | O8799: 372 | P8799: 10 | Q8799: 3.9 | R8799: 2013 | S8799: 9 | T8799: 28 | U8799: 41545 | V8799: =Main[[#This Row],[Average_Cost_for_two]] * VLOOKUP(Main[[#This Row],[Currency]],'Currency'!A:B,2,FALSE) -> 10 | W8799: =IF(Main[[#This Row],[Avg_Cost_USD]]<10,"Low", IF(Main[[#This Row],[Avg_Cost_USD]]<=30,"Medium","High")) -> Medium
A8800: 17334398 | B8800: Home Plate Grill | C8800: 216 | D8800: Dalton | E8800: Ringgold | F8800: -85.10794 | G8800: 34.915185 | H8800: American, BBQ, Southern | I8800: Dollar($) | J8800: No | K8800: No | L8800: No | M8800: No | N8800: 1 | O8800: 112 | P8800: 10 | Q8800: 4.2 | R8800: 2013 | S8800: 9 | T8800: 13 | U8800: 41530 | V8800: =Main[[#This Row],[Average_Cost_for_two]] * VLOOKUP(Main[[#This Row],[Currency]],'Currency'!A:B,2,FALSE) -> 10 | W8800: =IF(Main[[#This Row],[Avg_Cost_USD]]<10,"Low", IF(Main[[#This Row],[Avg_Cost_USD]]<=30,"Medium","High")) -> Medium
A8801: 17375104 | B8801: The Nacoochee Village Tavern & Pizzeria | C8801: 216 | D8801: Gainesville | E8801: Helen | F8801: -83.713498 | G8801: 34.691208 | H8801: Italian, Pizza, Sandwich | I8801: Dollar($) | J8801: No | K8801: No | L8801: No | M8801: No | N8801: 1 | O8801: 161 | P8801: 10 | Q8801: 4 | R8801: 2012 | S8801: 9 | T8801: 28 | U8801: 41180 | V8801: =Main[[#This Row],[Average_Cost_for_two]] * VLOOKUP(Main[[#This Row],[Currency]],'Currency'!A:B,2,FALSE) -> 10 | W8801: =IF(Main[[#This Row],[Avg_Cost_USD]]<10,"Low", IF(Main[[#This Row],[Avg_Cost_USD]]<=30,"Medium","High")) -> Medium
A8802: 17500759 | B8802: Ingleside Village Pizza | C8802: 216 | D8802: Macon | E8802: Macon | F8802: -83.657061 | G8802: 32.853896 | H8802: Pizza, Sandwich | I8802: Dollar($) | J8802: No | K8802: No | L8802: No | M8802: No | N8802: 1 | O8802: 478 | P8802: 10 | Q8802: 4.9 | R8802: 2016 | S8802: 9 | T8802: 6 | U8802: 42619 | V8802: =Main[[#This Row],[Average_Cost_for_two]] * VLOOKUP(Main[[#This Row],[Currency]],'Currency'!A:B,2,FALSE) -> 10 | W8802: =IF(Main[[#This Row],[Avg_Cost_USD]]<10,"Low", IF(Main[[#This Row],[Avg_Cost_USD]]<=30,"Medium","High")) -> Medium
A8803: 17621834 | B8803: Monterrey Mexican Restaurant | C8803: 216 | D8803: Sioux City | E8803: Sioux City | F8803: -96.3691 | G8803: 42.4351 | H8803: Mexican | I8803: Dollar($) | J8803: No | K8803: No | L8803: No | M8803: No | N8803: 1 | O8803: 117 | P8803: 10 | Q8803: 3.7 | R8803: 2016 | S8803: 9 | T8803: 23 | U8803: 42636 | V8803: =Main[[#This Row],[Average_Cost_for_two]] * VLOOKUP(Main[[#This Row],[Currency]],'Currency'!A:B,2,FALSE) -> 10 | W8803: =IF(Main[[#This Row],[Avg_Cost_USD]]<10,"Low", IF(Main[[#This Row],[Avg_Cost_USD]]<=30,"Medium","High")) -> Medium
A8804: 17095098 | B8804: Mazzaro's Italian Market | C8804: 216 | D8804: Tampa Bay | E8804: Kenwood | F8804: -82.673621 | G8804: 27.792047 | H8804: Italian, Deli | I8804: Dollar($) | J8804: No | K8804: No | L8804: No | M8804: No | N8804: 1 | O8804: 1424 | P8804: 10 | Q8804: 4.9 | R8804: 2011 | S8804: 9 | T8804: 25 | U8804: 40811 | V8804: =Main[[#This Row],[Average_Cost_for_two]] * VLOOKUP(Main[[#This Row],[Currency]],'Currency'!A:B,2,FALSE) -> 10 | W8804: =IF(Main[[#This Row],[Avg_Cost_USD]]<10,"Low", IF(Main[[#This Row],[Avg_Cost_USD]]<=30,"Medium","High")) -> Medium
A8805: 17697444 | B8805: Masala Grill & Coffee House | C8805: 216 | D8805: Waterloo | E8805: Cedar Falls | F8805: -92.456343 | G8805: 42.516908 | H8805: Indian, Middle Eastern | I8805: Dollar($) | J8805: No | K8805: No | L8805: No | M8805: No | N8805: 1 | O8805: 18 | P8805: 10 | Q8805: 3.2 | R8805: 2017 | S8805: 9 | T8805: 4 | U8805: 42982 | V8805: =Main[[#This Row],[Average_Cost_for_two]] * VLOOKUP(Main[[#This Row],[Currency]],'Currency'!A:B,2,FALSE) -> 10 | W8805: =IF(Main[[#This Row],[Avg_Cost_USD]]<10,"Low", IF(Main[[#This Row],[Avg_Cost_USD]]<=30,"Medium","High")) -> Medium
A8806: 17284409 | B8806: Guang Zhou Chinese Restaurant | C8806: 216 | D8806: Albany | E8806: Albany | F8806: -84.209146 | G8806: 31.615519 | H8806: Asian, Chinese, Vegetarian | I8806: Dollar($) | J8806: No | K8806: No | L8806: No | M8806: No | N8806: 1 | O8806: 141 | P8806: 10 | Q8806: 3.9 | R8806: 2010 | S8806: 8 | T8806: 13 | U8806: 40403 | V8806: =Main[[#This Row],[Average_Cost_for_two]] * VLOOKUP(Main[[#This Row],[Currency]],'Currency'!A:B,2,FALSE) -> 10 | W8806: =IF(Main[[#This Row],[Avg_Cost_USD]]<10,"Low", IF(Main[[#This Row],[Avg_Cost_USD]]<=30,"Medium","High")) -> Medium
A8807: 17284279 | B8807: Villa Gargano | C8807: 216 | D8807: Albany | E8807: Albany | F8807: -84.1757 | G8807: 31.5985 | H8807: Italian, Pizza | I8807: Dollar($) | J8807: No | K8807: No | L8807: No | M8807: No | N8807: 1 | O8807: 117 | P8807: 10 | Q8807: 3.7 | R8807: 2016 | S8807: 8 | T8807: 17 | U8807: 42599 | V8807: =Main[[#This Row],[Average_Cost_for_two]] * VLOOKUP(Main[[#This Row],[Currency]],'Currency'!A:B,2,FALSE) -> 10 | W8807: =IF(Main[[#This Row],[Avg_Cost_USD]]<10,"Low", IF(Main[[#This Row],[Avg_Cost_USD]]<=30,"Medium","High")) -> Medium
A8808: 17315995 | B8808: El Super Burrito | C8808: 216 | D8808: Cedar Rapids/Iowa City | E8808: Cedar Rapids | F8808: -91.7148 | G8808: 41.9748 | H8808: Mexican | I8808: Dollar($) | J8808: No | K8808: No | L8808: No | M8808: No | N8808: 1 | O8808: 190 | P8808: 10 | Q8808: 4.1 | R8808: 2011 | S8808: 8 | T8808: 16 | U8808: 40771 | V8808: =Main[[#This Row],[Average_Cost_for_two]] * VLOOKUP(Main[[#This Row],[Currency]],'Currency'!A:B,2,FALSE) -> 10 | W8808: =IF(Main[[#This Row],[Avg_Cost_USD]]<10,"Low", IF(Main[[#This Row],[Avg_Cost_USD]]<=30,"Medium","High")) -> Medium
... A8877: 17582546 | B8877: El Herradero | C8877: 216 | D8877: Pocatello | E8877: Pocatello | F8877: -112.4419 | G8877: 42.8774 | H8877: Mexican | I8877: Dollar($) | J8877: No | K8877: No | L8877: No | M8877: No | N8877: 1 | O8877: 365 | P8877: 10 | Q8877: 4.1 | R8877: 2011 | S8877: 2 | T8877: 8 | U8877: 40582 | V8877: =Main[[#This Row],[Average_Cost_for_two]] * VLOOKUP(Main[[#This Row],[Currency]],'Currency'!A:B,2,FALSE) -> 10 | W8877: =IF(Main[[#This Row],[Avg_Cost_USD]]<10,"Low", IF(Main[[#This Row],[Avg_Cost_USD]]<=30,"Medium","High")) -> Medium
A8878: 17142698 | B8878: Leonard's Bakery | C8878: 216 | D8878: Rest of Hawaii | E8878: Kaimuki | F8878: -157.81343 | G8878: 21.284586 | I8878: Dollar($) | J8878: No | K8878: No | L8878: No | M8878: No | N8878: 1 | O8878: 707 | P8878: 10 | Q8878: 4.7 | R8878: 2010 | S8878: 2 | T8878: 21 | U8878: 40230 | V8878: =Main[[#This Row],[Average_Cost_for_two]] * VLOOKUP(Main[[#This Row],[Currency]],'Currency'!A:B,2,FALSE) -> 10 | W8878: =IF(Main[[#This Row],[Avg_Cost_USD]]<10,"Low", IF(Main[[#This Row],[Avg_Cost_USD]]<=30,"Medium","High")) -> Medium
A8879: 17293915 | B8879: The Royal Peasant | C8879: 216 | D8879: Athens | E8879: Athens | F8879: -83.38728 | G8879: 33.937502 | H8879: Bar Food | I8879: Dollar($) | J8879: No | K8879: No | L8879: No | M8879: No | N8879: 1 | O8879: 546 | P8879: 10 | Q8879: 4.4 | R8879: 2013 | S8879: 1 | T8879: 15 | U8879: 41289 | V8879: =Main[[#This Row],[Average_Cost_for_two]] * VLOOKUP(Main[[#This Row],[Currency]],'Currency'!A:B,2,FALSE) -> 10 | W8879: =IF(Main[[#This Row],[Avg_Cost_USD]]<10,"Low", IF(Main[[#This Row],[Avg_Cost_USD]]<=30,"Medium","High")) -> Medium
...

Sheet Currency
A1: Currency | B1: USD Rate
A2: Indian Rupees(Rs.) | B2: 0.012
A3: Dollar($) | B3: 1
A4: Pounds(Œ£) | B4: 1.24
A5: NewZealand($) | B5: 0.6
A6: Emirati Diram(AED) | B6: 0.27
A7: Brazilian Real(R$) | B7: 0.2
A8: Turkish Lira(TL) | B8: 0.05
A9: Qatari Rial(QR) | B9: 0.27
A10: Rand(R) | B10: 0.051
A11: Botswana Pula(P) | B11: 0.073
A12: Sri Lankan Rupee(LKR) | B12: 0.0034
A13: Indonesian Rupiah(IDR) | B13: 6.7e-05

Sheet Calendar1
A1: Date | B1: Year | C1: MonthNo | D1: MonthFullName | E1: Quarter | F1: YearMonth | G1: WeekdayNo | H1: WeekdayName | I1: FinancialMonth | J1: FinancialQuarter
A2: =MIN(Main[Date]) -> 40179 | B2: =YEAR(A2) -> 2010 | C2: =MONTH(A2) -> 1 | D2: =TEXT(A2,"mmmm") -> January | E2: ="Q"&ROUNDUP(MONTH(A2)/3,0) -> Q1 | F2: =TEXT(A2,"yyyy-mmm") -> 2010-Jan | G2: =WEEKDAY(A2) -> 6 | H2: =TEXT(A2,"dddd") -> Friday | I2: ="FM"&IF(MONTH(A2)>=4,MONTH(A2)-3,MONTH(A2)+9) -> FM10 | J2: ="FQ-"&ROUNDUP(IF(MONTH(A2)>=4,MONTH(A2)-3,MONTH(A2)+9)/3,0) -> FQ-4
A3: =A2+1 -> 40180 | B3: =YEAR(A3) -> 2010 | C3: =MONTH(A3) -> 1 | D3: =TEXT(A3,"mmmm") -> January | E3: ="Q"&ROUNDUP(MONTH(A3)/3,0) -> Q1 | F3: =TEXT(A3,"yyyy-mmm") -> 2010-Jan | G3: =WEEKDAY(A3) -> 7 | H3: =TEXT(A3,"dddd") -> Saturday | I3: ="FM"&IF(MONTH(A3)>=4,MONTH(A3)-3,MONTH(A3)+9) -> FM10 | J3: ="FQ-"&ROUNDUP(IF(MONTH(A3)>=4,MONTH(A3)-3,MONTH(A3)+9)/3,0) -> FQ-4
A4: =A3+1 -> 40181 | B4: =YEAR(A4) -> 2010 | C4: =MONTH(A4) -> 1 | D4: =TEXT(A4,"mmmm") -> January | E4: ="Q"&ROUNDUP(MONTH(A4)/3,0) -> Q1 | F4: =TEXT(A4,"yyyy-mmm") -> 2010-Jan | G4: =WEEKDAY(A4) -> 1 | H4: =TEXT(A4,"dddd") -> Sunday | I4: ="FM"&IF(MONTH(A4)>=4,MONTH(A4)-3,MONTH(A4)+9) -> FM10 | J4: ="FQ-"&ROUNDUP(IF(MONTH(A4)>=4,MONTH(A4)-3,MONTH(A4)+9)/3,0) -> FQ-4
A5: =A4+1 -> 40182 | B5: =YEAR(A5) -> 2010 | C5: =MONTH(A5) -> 1 | D5: =TEXT(A5,"mmmm") -> January | E5: ="Q"&ROUNDUP(MONTH(A5)/3,0) -> Q1 | F5: =TEXT(A5,"yyyy-mmm") -> 2010-Jan | G5: =WEEKDAY(A5) -> 2 | H5: =TEXT(A5,"dddd") -> Monday | I5: ="FM"&IF(MONTH(A5)>=4,MONTH(A5)-3,MONTH(A5)+9) -> FM10 | J5: ="FQ-"&ROUNDUP(IF(MONTH(A5)>=4,MONTH(A5)-3,MONTH(A5)+9)/3,0) -> FQ-4
A6: =A5+1 -> 40183 | B6: =YEAR(A6) -> 2010 | C6: =MONTH(A6) -> 1 | D6: =TEXT(A6,"mmmm") -> January | E6: ="Q"&ROUNDUP(MONTH(A6)/3,0) -> Q1 | F6: =TEXT(A6,"yyyy-mmm") -> 2010-Jan | G6: =WEEKDAY(A6) -> 3 | H6: =TEXT(A6,"dddd") -> Tuesday | I6: ="FM"&IF(MONTH(A6)>=4,MONTH(A6)-3,MONTH(A6)+9) -> FM10 | J6: ="FQ-"&ROUNDUP(IF(MONTH(A6)>=4,MONTH(A6)-3,MONTH(A6)+9)/3,0) -> FQ-4
A7: =A6+1 -> 40184 | B7: =YEAR(A7) -> 2010 | C7: =MONTH(A7) -> 1 | D7: =TEXT(A7,"mmmm") -> January | E7: ="Q"&ROUNDUP(MONTH(A7)/3,0) -> Q1 | F7: =TEXT(A7,"yyyy-mmm") -> 2010-Jan | G7: =WEEKDAY(A7) -> 4 | H7: =TEXT(A7,"dddd") -> Wednesday | I7: ="FM"&IF(MONTH(A7)>=4,MONTH(A7)-3,MONTH(A7)+9) -> FM10 | J7: ="FQ-"&ROUNDUP(IF(MONTH(A7)>=4,MONTH(A7)-3,MONTH(A7)+9)/3,0) -> FQ-4
A8: =A7+1 -> 40185 | B8: =YEAR(A8) -> 2010 | C8: =MONTH(A8) -> 1 | D8: =TEXT(A8,"mmmm") -> January | E8: ="Q"&ROUNDUP(MONTH(A8)/3,0) -> Q1 | F8: =TEXT(A8,"yyyy-mmm") -> 2010-Jan | G8: =WEEKDAY(A8) -> 5 | H8: =TEXT(A8,"dddd") -> Thursday | I8: ="FM"&IF(MONTH(A8)>=4,MONTH(A8)-3,MONTH(A8)+9) -> FM10 | J8: ="FQ-"&ROUNDUP(IF(MONTH(A8)>=4,MONTH(A8)-3,MONTH(A8)+9)/3,0) -> FQ-4 | L8: Min Date | M8: =MIN(Main[Date]) -> 40179
A9: =A8+1 -> 40186 | B9: =YEAR(A9) -> 2010 | C9: =MONTH(A9) -> 1 | D9: =TEXT(A9,"mmmm") -> January | E9: ="Q"&ROUNDUP(MONTH(A9)/3,0) -> Q1 | F9: =TEXT(A9,"yyyy-mmm") -> 2010-Jan | G9: =WEEKDAY(A9) -> 6 | H9: =TEXT(A9,"dddd") -> Friday | I9: ="FM"&IF(MONTH(A9)>=4,MONTH(A9)-3,MONTH(A9)+9) -> FM10 | J9: ="FQ-"&ROUNDUP(IF(MONTH(A9)>=4,MONTH(A9)-3,MONTH(A9)+9)/3,0) -> FQ-4 | L9: Max Date | M9: =MAX(Main[Date]) -> 43462
A10: =A9+1 -> 40187 | B10: =YEAR(A10) -> 2010 | C10: =MONTH(A10) -> 1 | D10: =TEXT(A10,"mmmm") -> January | E10: ="Q"&ROUNDUP(MONTH(A10)/3,0) -> Q1 | F10: =TEXT(A10,"yyyy-mmm") -> 2010-Jan | G10: =WEEKDAY(A10) -> 7 | H10: =TEXT(A10,"dddd") -> Saturday | I10: ="FM"&IF(MONTH(A10)>=4,MONTH(A10)-3,MONTH(A10)+9) -> FM10 | J10: ="FQ-"&ROUNDUP(IF(MONTH(A10)>=4,MONTH(A10)-3,MONTH(A10)+9)/3,0) -> FQ-4
A11: =A10+1 -> 40188 | B11: =YEAR(A11) -> 2010 | C11: =MONTH(A11) -> 1 | D11: =TEXT(A11,"mmmm") -> January | E11: ="Q"&ROUNDUP(MONTH(A11)/3,0) -> Q1 | F11: =TEXT(A11,"yyyy-mmm") -> 2010-Jan | G11: =WEEKDAY(A11) -> 1 | H11: =TEXT(A11,"dddd") -> Sunday | I11: ="FM"&IF(MONTH(A11)>=4,MONTH(A11)-3,MONTH(A11)+9) -> FM10 | J11: ="FQ-"&ROUNDUP(IF(MONTH(A11)>=4,MONTH(A11)-3,MONTH(A11)+9)/3,0) -> FQ-4
A12: =A11+1 -> 40189 | B12: =YEAR(A12) -> 2010 | C12: =MONTH(A12) -> 1 | D12: =TEXT(A12,"mmmm") -> January | E12: ="Q"&ROUNDUP(MONTH(A12)/3,0) -> Q1 | F12: =TEXT(A12,"yyyy-mmm") -> 2010-Jan | G12: =WEEKDAY(A12) -> 2 | H12: =TEXT(A12,"dddd") -> Monday | I12: ="FM"&IF(MONTH(A12)>=4,MONTH(A12)-3,MONTH(A12)+9) -> FM10 | J12: ="FQ-"&ROUNDUP(IF(MONTH(A12)>=4,MONTH(A12)-3,MONTH(A12)+9)/3,0) -> FQ-4
A13: =A12+1 -> 40190 | B13: =YEAR(A13) -> 2010 | C13: =MONTH(A13) -> 1 | D13: =TEXT(A13,"mmmm") -> January | E13: ="Q"&ROUNDUP(MONTH(A13)/3,0) -> Q1 | F13: =TEXT(A13,"yyyy-mmm") -> 2010-Jan | G13: =WEEKDAY(A13) -> 3 | H13: =TEXT(A13,"dddd") -> Tuesday | I13: ="FM"&IF(MONTH(A13)>=4,MONTH(A13)-3,MONTH(A13)+9) -> FM10 | J13: ="FQ-"&ROUNDUP(IF(MONTH(A13)>=4,MONTH(A13)-3,MONTH(A13)+9)/3,0) -> FQ-4
A14: =A13+1 -> 40191 | B14: =YEAR(A14) -> 2010 | C14: =MONTH(A14) -> 1 | D14: =TEXT(A14,"mmmm") -> January | E14: ="Q"&ROUNDUP(MONTH(A14)/3,0) -> Q1 | F14: =TEXT(A14,"yyyy-mmm") -> 2010-Jan | G14: =WEEKDAY(A14) -> 4 | H14: =TEXT(A14,"dddd") -> Wednesday | I14: ="FM"&IF(MONTH(A14)>=4,MONTH(A14)-3,MONTH(A14)+9) -> FM10 | J14: ="FQ-"&ROUNDUP(IF(MONTH(A14)>=4,MONTH(A14)-3,MONTH(A14)+9)/3,0) -> FQ-4
A15: =A14+1 -> 40192 | B15: =YEAR(A15) -> 2010 | C15: =MONTH(A15) -> 1 | D15: =TEXT(A15,"mmmm") -> January | E15: ="Q"&ROUNDUP(MONTH(A15)/3,0) -> Q1 | F15: =TEXT(A15,"yyyy-mmm") -> 2010-Jan | G15: =WEEKDAY(A15) -> 5 | H15: =TEXT(A15,"dddd") -> Thursday | I15: ="FM"&IF(MONTH(A15)>=4,MONTH(A15)-3,MONTH(A15)+9) -> FM10 | J15: ="FQ-"&ROUNDUP(IF(MONTH(A15)>=4,MONTH(A15)-3,MONTH(A15)+9)/3,0) -> FQ-4
A16: =A15+1 -> 40193 | B16: =YEAR(A16) -> 2010 | C16: =MONTH(A16) -> 1 | D16: =TEXT(A16,"mmmm") -> January | E16: ="Q"&ROUNDUP(MONTH(A16)/3,0) -> Q1 | F16: =TEXT(A16,"yyyy-mmm") -> 2010-Jan | G16: =WEEKDAY(A16) -> 6 | H16: =TEXT(A16,"dddd") -> Friday | I16: ="FM"&IF(MONTH(A16)>=4,MONTH(A16)-3,MONTH(A16)+9) -> FM10 | J16: ="FQ-"&ROUNDUP(IF(MONTH(A16)>=4,MONTH(A16)-3,MONTH(A16)+9)/3,0) -> FQ-4
A17: =A16+1 -> 40194 | B17: =YEAR(A17) -> 2010 | C17: =MONTH(A17) -> 1 | D17: =TEXT(A17,"mmmm") -> January | E17: ="Q"&ROUNDUP(MONTH(A17)/3,0) -> Q1 | F17: =TEXT(A17,"yyyy-mmm") -> 2010-Jan | G17: =WEEKDAY(A17) -> 7 | H17: =TEXT(A17,"dddd") -> Saturday | I17: ="FM"&IF(MONTH(A17)>=4,MONTH(A17)-3,MONTH(A17)+9) -> FM10 | J17: ="FQ-"&ROUNDUP(IF(MONTH(A17)>=4,MONTH(A17)-3,MONTH(A17)+9)/3,0) -> FQ-4
A18: =A17+1 -> 40195 | B18: =YEAR(A18) -> 2010 | C18: =MONTH(A18) -> 1 | D18: =TEXT(A18,"mmmm") -> January | E18: ="Q"&ROUNDUP(MONTH(A18)/3,0) -> Q1 | F18: =TEXT(A18,"yyyy-mmm") -> 2010-Jan | G18: =WEEKDAY(A18) -> 1 | H18: =TEXT(A18,"dddd") -> Sunday | I18: ="FM"&IF(MONTH(A18)>=4,MONTH(A18)-3,MONTH(A18)+9) -> FM10 | J18: ="FQ-"&ROUNDUP(IF(MONTH(A18)>=4,MONTH(A18)-3,MONTH(A18)+9)/3,0) -> FQ-4
A19: =A18+1 -> 40196 | B19: =YEAR(A19) -> 2010 | C19: =MONTH(A19) -> 1 | D19: =TEXT(A19,"mmmm") -> January | E19: ="Q"&ROUNDUP(MONTH(A19)/3,0) -> Q1 | F19: =TEXT(A19,"yyyy-mmm") -> 2010-Jan | G19: =WEEKDAY(A19) -> 2 | H19: =TEXT(A19,"dddd") -> Monday | I19: ="FM"&IF(MONTH(A19)>=4,MONTH(A19)-3,MONTH(A19)+9) -> FM10 | J19: ="FQ-"&ROUNDUP(IF(MONTH(A19)>=4,MONTH(A19)-3,MONTH(A19)+9)/3,0) -> FQ-4
A20: =A19+1 -> 40197 | B20: =YEAR(A20) -> 2010 | C20: =MONTH(A20) -> 1 | D20: =TEXT(A20,"mmmm") -> January | E20: ="Q"&ROUNDUP(MONTH(A20)/3,0) -> Q1 | F20: =TEXT(A20,"yyyy-mmm") -> 2010-Jan | G20: =WEEKDAY(A20) -> 3 | H20: =TEXT(A20,"dddd") -> Tuesday | I20: ="FM"&IF(MONTH(A20)>=4,MONTH(A20)-3,MONTH(A20)+9) -> FM10 | J20: ="FQ-"&ROUNDUP(IF(MONTH(A20)>=4,MONTH(A20)-3,MONTH(A20)+9)/3,0) -> FQ-4
A21: =A20+1 -> 40198 | B21: =YEAR(A21) -> 2010 | C21: =MONTH(A21) -> 1 | D21: =TEXT(A21,"mmmm") -> January | E21: ="Q"&ROUNDUP(MONTH(A21)/3,0) -> Q1 | F21: =TEXT(A21,"yyyy-mmm") -> 2010-Jan | G21: =WEEKDAY(A21) -> 4 | H21: =TEXT(A21,"dddd") -> Wednesday | I21: ="FM"&IF(MONTH(A21)>=4,MONTH(A21)-3,MONTH(A21)+9) -> FM10 | J21: ="FQ-"&ROUNDUP(IF(MONTH(A21)>=4,MONTH(A21)-3,MONTH(A21)+9)/3,0) -> FQ-4
... A3285: =A3284+1 -> 43462 | B3285: =YEAR(A3285) -> 2018 | C3285: =MONTH(A3285) -> 12 | D3285: =TEXT(A3285,"mmmm") -> December | E3285: ="Q"&ROUNDUP(MONTH(A3285)/3,0) -> Q4 | F3285: =TEXT(A3285,"yyyy-mmm") -> 2018-Dec | G3285: =WEEKDAY(A3285) -> 6 | H3285: =TEXT(A3285,"dddd") -> Friday | I3285: ="FM"&IF(MONTH(A3285)>=4,MONTH(A3285)-3,MONTH(A3285)+9) -> FM9 | J3285: ="FQ-"&ROUNDUP(IF(MONTH(A3285)>=4,MONTH(A3285)-3,MONTH(A3285)+9)/3,0) -> FQ-3

Sheet Country
A1: CountryID | B1: Countryname
A2: 1 | B2: India
A3: 14 | B3: Australia
A4: 30 | B4: Brazil
A5: 37 | B5: Canada
A6: 94 | B6: Indonasia
A7: 148 | B7: New Zealand
A8: 162 | B8: Phillipines
A9: 166 | B9: Qatar
A10: 184 | B10: Singapore
A11: 189 | B11: South Africa
A12: 191 | B12: Sri lanka
A13: 208 | B13: Turkey
... A16: 216 | B16: United States

Sheet Q4
A1: Row Labels | B1: Count of RestaurantID
A2: Australia
A3: Armidale | B3: 1
A4: Balingup | B4: 1
A5: Beechworth | B5: 1
A6: Dicky Beach | B6: 1
A7: East Ballina | B7: 1
A8: Flaxton | B8: 1
A9: Forrest | B9: 1
A10: Hepburn Springs | B10: 2
A11: Huskisson | B11: 1
A12: Inverloch | B12: 1
A13: Lakes Entrance | B13: 1
A14: Lorn | B14: 1
... A25: Victor Harbor | B25: 1
A26: Brazil
A27: Brasí_lia | B27: 20
A28: Rio de Janeiro | B28: 20
A29: Sí£o Paulo | B29: 20
A30: Canada
A31: Chatham-Kent | B31: 1
A32: Consort | B32: 1
A33: Vineland Station | B33: 1
A34: Yorkton | B34: 1
A35: India
A36: Agra | B36: 20
A37: Ahmedabad | B37: 21
A38: Allahabad | B38: 20
A39: Amritsar | B39: 21
A40: Aurangabad | B40: 20
A41: Bangalore | B41: 20
A42: Bhopal | B42: 20
A43: Bhubaneshwar | B43: 21
A44: Chandigarh | B44: 18
A45: Chennai | B45: 20
A46: Coimbatore | B46: 20
A47: Dehradun | B47: 20
... A78: Vizag | B78: 20
A79: Indonasia
A80: Bandung | B80: 1
A81: Bogor | B81: 2
A82: Jakarta | B82: 16
A83: Tangerang | B83: 2
A84: New Zealand
A85: Auckland | B85: 20
A86: Wellington City | B86: 20
A87: Phillipines
A88: Makati City | B88: 2
A89: Mandaluyong City | B89: 4
A90: Pasay City | B90: 3
A91: Pasig City | B91: 3
A92: Quezon City | B92: 1
A93: San Juan City | B93: 2
A94: Santa Rosa | B94: 2
A95: Tagaytay City | B95: 1
A96: Taguig City | B96: 4
A97: Qatar
A98: Doha | B98: 20
A99: Singapore
A100: Singapore | B100: 20
A101: South Africa
A102: Cape Town | B102: 20
A103: Inner City | B103: 2
A104: Johannesburg | B104: 6
A105: Pretoria | B105: 20
A106: Randburg | B106: 1
A107: Sandton | B107: 11
A108: Sri lanka
A109: Colombo | B109: 20
A110: Turkey
A111: Ankara | B111: 20
A112: ÛÁstanbul | B112: 14
A113: United Arab Emirates
A114: Abu Dhabi | B114: 20
A115: Dubai | B115: 20
A116: Sharjah | B116: 20
A117: United Kingdom
A118: Birmingham | B118: 20
A119: Edinburgh | B119: 20
A120: London | B120: 20
A121: Manchester | B121: 20
A122: United States
A123: Albany | B123: 20
A124: Athens | B124: 20
A125: Augusta | B125: 20
A126: Boise | B126: 20
A127: Cedar Rapids/Iowa City | B127: 20
A128: Clatskanie | B128: 1
A129: Cochrane | B129: 1
A130: Columbus | B130: 20
A131: Dalton | B131: 20
A132: Davenport | B132: 20
A133: Des Moines | B133: 20
A134: Dubuque | B134: 20
... A158: Grand Total | B158: 9551

Sheet Q5
A3: Row Labels | B3: Count of RestaurantID
A4: 2010
A5: Q1
A6: February | B6: 77
A7: January | B7: 83
A8: March | B8: 90
A9: Q2
A10: April | B10: 91
A11: June | B11: 89
A12: May | B12: 77
A13: Q3
A14: August | B14: 97
A15: July | B15: 96
A16: September | B16: 90
A17: Q4
A18: December | B18: 91
A19: November | B19: 103
A20: October | B20: 96
A21: 2011
A22: Q1
A23: February | B23: 87
A24: January | B24: 76
A25: March | B25: 119
A26: Q2
A27: April | B27: 102
A28: June | B28: 90
A29: May | B29: 80
A30: Q3
A31: August | B31: 94
A32: July | B32: 107
A33: September | B33: 107
A34: Q4
A35: December | B35: 75
A36: November | B36: 76
A37: October | B37: 85
A38: 2012
A39: Q1
A40: February | B40: 69
A41: January | B41: 73
A42: March | B42: 87
A43: Q2
A44: April | B44: 91
A45: June | B45: 89
A46: May | B46: 89
A47: Q3
A48: August | B48: 97
A49: July | B49: 74
A50: September | B50: 88
A51: Q4
A52: December | B52: 96
A53: November | B53: 82
A54: October | B54: 87
A55: 2013
A56: Q1
A57: February | B57: 82
A58: January | B58: 94
A59: March | B59: 98
A60: Q2
A61: April | B61: 87
A62: June | B62: 78
A63: May | B63: 107
A64: Q3
A65: August | B65: 79
A66: July | B66: 81
A67: September | B67: 95
A68: Q4
A69: December | B69: 95
A70: November | B70: 91
A71: October | B71: 74
A72: 2014
A73: Q1
A74: February | B74: 91
A75: January | B75: 90
A76: March | B76: 101
A77: Q2
A78: April | B78: 85
A79: June | B79: 93
A80: May | B80: 73
A81: Q3
A82: August | B82: 86
A83: July | B83: 78
A84: September | B84: 93
A85: Q4
A86: December | B86: 83
A87: November | B87: 93
A88: October | B88: 85
A89: 2015
A90: Q1
A91: February | B91: 80
A92: January | B92: 82
A93: March | B93: 83
A94: Q2
A95: April | B95: 81
A96: June | B96: 80
A97: May | B97: 87
A98: Q3
A99: August | B99: 85
A100: July | B100: 85
A101: September | B101: 88
A102: Q4
...

Sheet Q6
A3: Row Labels | B3: Count of RestaurantID
A4: 1 | B4: 2148
A5: 1.8 | B5: 1
A6: 1.9 | B6: 2
A7: 2 | B7: 7
A8: 2.1 | B8: 15
A9: 2.2 | B9: 27
A10: 2.3 | B10: 47
A11: 2.4 | B11: 87
A12: 2.5 | B12: 110
A13: 2.6 | B13: 191
A14: 2.7 | B14: 250
A15: 2.8 | B15: 315
... A36: 4.9 | B36: 61
A37: Grand Total | B37: 9551

Sheet Q7
A3: Row Labels | B3: Count of RestaurantID
A4: High | B4: 461
A5: Low | B5: 7143
A6: Medium | B6: 1947
A7: Grand Total | B7: 9551

Sheet Q8
A3: Row Labels | B3: Count of RestaurantID
A4: No | B4: 0.87875615
A5: Yes | B5: 0.12124385
A6: Grand Total | B6: 1

Sheet Q9
A1: Row Labels | B1: Count of RestaurantID
A2: No | B2: 0.74337766
A3: Yes | B3: 0.25662234
A4: Grand Total | B4: 1

Sheet Sheet1
A1: Data returned for Count of RestaurantID, Australia - Hepburn Springs (First 1000 rows).
A3: Main[RestaurantID] | B3: Main[RestaurantName] | C3: Main[CountryCode] | D3: Main[City] | E3: Main[Locality] | F3: Main[Longitude] | G3: Main[Latitude] | H3: Main[Cuisines] | I3: Main[Currency] | J3: Main[Has_Table_booking] | K3: Main[Has_Online_delivery] | L3: Main[Is_delivering_now] | M3: Main[Switch_to_order_menu] | N3: Main[Price_range] | O3: Main[Votes] | P3: Main[Average_Cost_for_two] | Q3: Main[Rating] | R3: Main[Year Opening] | S3: Main[Month Opening] | T3: Main[Day Opening] | U3: Main[Date]
A4: 16604358 | B4: Blue Bean Love Cafe | C4: 14 | D4: Hepburn Springs | E4: Hepburn Springs | F4: 144.1387 | G4: -37.312327 | H4: Cafe, Coffee and Tea, Modern Australian | I4: Dollar($) | J4: No | K4: No | L4: No | M4: No | N4: 2 | O4: 192 | P4: 20 | Q4: 3.8 | R4: 2012 | S4: 8 | T4: 4 | U4: 41125
A5: 16604896 | B5: La Trattoria of Lavandula | C5: 14 | D5: Hepburn Springs | E5: Hepburn Springs | F5: 144.11006 | G5: -37.275494 | H5: Italian, Fusion, Cafe | I5: Dollar($) | J5: No | K5: No | L5: No | M5: No | N5: 1 | O5: 93 | P5: 7 | Q5: 3.8 | R5: 2013 | S5: 6 | T5: 13 | U5: 41438
